{"objectIdFieldName":"OBJECTID","uniqueIdField":{"name":"OBJECTID","isSystemMaintained":true},"globalIdFieldName":"GlobalID","geometryType":"esriGeometryPoint","spatialReference":{"wkid":4326,"latestWkid":4326},"fields":[{"name":"OBJECTID","type":"esriFieldTypeOID","alias":"OBJECTID","sqlType":"sqlTypeOther","domain":null,"defaultValue":null},{"name":"ADM0_NAME","type":"esriFieldTypeString","alias":"ADM0_NAME","sqlType":"sqlTypeOther","length":255,"domain":null,"defaultValue":null},{"name":"DateOfDataEntry","type":"esriFieldTypeDate","alias":"DateOfDataEntry","sqlType":"sqlTypeOther","length":8,"domain":null,"defaultValue":null},{"name":"cum_conf","type":"esriFieldTypeInteger","alias":"cum_conf","sqlType":"sqlTypeOther","domain":null,"defaultValue":null},{"name":"NewCase","type":"esriFieldTypeInteger","alias":"NewCase","sqlType":"sqlTypeOther","domain":null,"defaultValue":null},{"name":"CENTER_LON","type":"esriFieldTypeDouble","alias":"CENTER_LON","sqlType":"sqlTypeOther","domain":null,"defaultValue":null},{"name":"CENTER_LAT","type":"esriFieldTypeDouble","alias":"CENTER_LAT","sqlType":"sqlTypeOther","domain":null,"defaultValue":null},{"name":"ADM0_VIZ_NAME","type":"esriFieldTypeString","alias":"ADM0_VIZ_NAME","sqlType":"sqlTypeOther","length":255,"domain":null,"defaultValue":null},{"name":"GUID","type":"esriFieldTypeGUID","alias":"GUID","sqlType":"sqlTypeOther","length":38,"domain":null,"defaultValue":null},{"name":"Short_Name_ZH","type":"esriFieldTypeString","alias":"Short_Name_ZH","sqlType":"sqlTypeOther","length":255,"domain":null,"defaultValue":null},{"name":"Short_Name_FR","type":"esriFieldTypeString","alias":"Short_Name_FR","sqlType":"sqlTypeOther","length":255,"domain":null,"defaultValue":null},{"name":"Short_Name_ES","type":"esriFieldTypeString","alias":"Short_Name_ES","sqlType":"sqlTypeOther","length":255,"domain":null,"defaultValue":null},{"name":"Short_Name_RU","type":"esriFieldTypeString","alias":"Short_Name_RU","sqlType":"sqlTypeOther","length":255,"domain":null,"defaultValue":null},{"name":"Short_Name_AR","type":"esriFieldTypeString","alias":"Short_Name_AR","sqlType":"sqlTypeOther","length":255,"domain":null,"defaultValue":null},{"name":"GlobalID","type":"esriFieldTypeGlobalID","alias":"GlobalID","sqlType":"sqlTypeOther","length":38,"domain":null,"defaultValue":null}],"features":[{"attributes":{"OBJECTID":742,"ADM0_NAME":"CHINA","DateOfDataEntry":1579737600000,"cum_conf":574,"NewCase":574,"CENTER_LON":103.8934731,"CENTER_LAT":36.51870146,"ADM0_VIZ_NAME":"China","GUID":"af40da08-eeb3-40e9-bd59-41c06c17191f","Short_Name_ZH":"中国","Short_Name_FR":"Chine","Short_Name_ES":"China","Short_Name_RU":"Китай","Short_Name_AR":"الصين","GlobalID":"35a32378-a4ca-45c4-a9ed-694eb2bfc9cb"},"geometry":{"x":103.89347310100004,"y":36.518701460000045}},{"attributes":{"OBJECTID":743,"ADM0_NAME":"CHINA","DateOfDataEntry":1579824000000,"cum_conf":835,"NewCase":261,"CENTER_LON":103.8934731,"CENTER_LAT":36.51870146,"ADM0_VIZ_NAME":"China","GUID":"af40da08-eeb3-40e9-bd59-41c06c17191f","Short_Name_ZH":"中国","Short_Name_FR":"Chine","Short_Name_ES":"China","Short_Name_RU":"Китай","Short_Name_AR":"الصين","GlobalID":"dbdc7127-8e2e-4380-b171-bb35f16a0b74"},"geometry":{"x":103.89347310100004,"y":36.518701460000045}},{"attributes":{"OBJECTID":744,"ADM0_NAME":"CHINA","DateOfDataEntry":1579910400000,"cum_conf":1297,"NewCase":462,"CENTER_LON":103.8934731,"CENTER_LAT":36.51870146,"ADM0_VIZ_NAME":"China","GUID":"af40da08-eeb3-40e9-bd59-41c06c17191f","Short_Name_ZH":"中国","Short_Name_FR":"Chine","Short_Name_ES":"China","Short_Name_RU":"Китай","Short_Name_AR":"الصين","GlobalID":"293f5a75-1a39-4bca-9240-b5b86a2e8630"},"geometry":{"x":103.89347310100004,"y":36.518701460000045}},{"attributes":{"OBJECTID":745,"ADM0_NAME":"CHINA","DateOfDataEntry":1579996800000,"cum_conf":1985,"NewCase":688,"CENTER_LON":103.8934731,"CENTER_LAT":36.51870146,"ADM0_VIZ_NAME":"China","GUID":"af40da08-eeb3-40e9-bd59-41c06c17191f","Short_Name_ZH":"中国","Short_Name_FR":"Chine","Short_Name_ES":"China","Short_Name_RU":"Китай","Short_Name_AR":"الصين","GlobalID":"6b2b7985-2644-48a7-8e10-b32c85e504a1"},"geometry":{"x":103.89347310100004,"y":36.518701460000045}},{"attributes":{"OBJECTID":746,"ADM0_NAME":"CHINA","DateOfDataEntry":1580083200000,"cum_conf":2761,"NewCase":776,"CENTER_LON":103.8934731,"CENTER_LAT":36.51870146,"ADM0_VIZ_NAME":"China","GUID":"af40da08-eeb3-40e9-bd59-41c06c17191f","Short_Name_ZH":"中国","Short_Name_FR":"Chine","Short_Name_ES":"China","Short_Name_RU":"Китай","Short_Name_AR":"الصين","GlobalID":"c2531d8c-2c3c-4400-ae3d-6b1b3f5f447e"},"geometry":{"x":103.89347310100004,"y":36.518701460000045}},{"attributes":{"OBJECTID":747,"ADM0_NAME":"CHINA","DateOfDataEntry":1580169600000,"cum_conf":4537,"NewCase":1776,"CENTER_LON":103.8934731,"CENTER_LAT":36.51870146,"ADM0_VIZ_NAME":"China","GUID":"af40da08-eeb3-40e9-bd59-41c06c17191f","Short_Name_ZH":"中国","Short_Name_FR":"Chine","Short_Name_ES":"China","Short_Name_RU":"Китай","Short_Name_AR":"الصين","GlobalID":"82122213-e9e8-4180-9b9b-73449789839a"},"geometry":{"x":103.89347310100004,"y":36.518701460000045}},{"attributes":{"OBJECTID":748,"ADM0_NAME":"CHINA","DateOfDataEntry":1580256000000,"cum_conf":5997,"NewCase":1460,"CENTER_LON":103.8934731,"CENTER_LAT":36.51870146,"ADM0_VIZ_NAME":"China","GUID":"af40da08-eeb3-40e9-bd59-41c06c17191f","Short_Name_ZH":"中国","Short_Name_FR":"Chine","Short_Name_ES":"China","Short_Name_RU":"Китай","Short_Name_AR":"الصين","GlobalID":"c272ac53-f767-47f2-90ef-8f227c7df12f"},"geometry":{"x":103.89347310100004,"y":36.518701460000045}},{"attributes":{"OBJECTID":749,"ADM0_NAME":"CHINA","DateOfDataEntry":1580342400000,"cum_conf":7736,"NewCase":1739,"CENTER_LON":103.8934731,"CENTER_LAT":36.51870146,"ADM0_VIZ_NAME":"China","GUID":"af40da08-eeb3-40e9-bd59-41c06c17191f","Short_Name_ZH":"中国","Short_Name_FR":"Chine","Short_Name_ES":"China","Short_Name_RU":"Китай","Short_Name_AR":"الصين","GlobalID":"05e34f84-5ca6-4d58-8b3a-0c51d9f2e80a"},"geometry":{"x":103.89347310100004,"y":36.518701460000045}},{"attributes":{"OBJECTID":750,"ADM0_NAME":"CHINA","DateOfDataEntry":1580428800000,"cum_conf":9720,"NewCase":1984,"CENTER_LON":103.8934731,"CENTER_LAT":36.51870146,"ADM0_VIZ_NAME":"China","GUID":"af40da08-eeb3-40e9-bd59-41c06c17191f","Short_Name_ZH":"中国","Short_Name_FR":"Chine","Short_Name_ES":"China","Short_Name_RU":"Китай","Short_Name_AR":"الصين","GlobalID":"3b77fcc4-89ac-4aed-924d-49f8e7c949cc"},"geometry":{"x":103.89347310100004,"y":36.518701460000045}},{"attributes":{"OBJECTID":751,"ADM0_NAME":"CHINA","DateOfDataEntry":1580515200000,"cum_conf":11821,"NewCase":2101,"CENTER_LON":103.8934731,"CENTER_LAT":36.51870146,"ADM0_VIZ_NAME":"China","GUID":"af40da08-eeb3-40e9-bd59-41c06c17191f","Short_Name_ZH":"中国","Short_Name_FR":"Chine","Short_Name_ES":"China","Short_Name_RU":"Китай","Short_Name_AR":"الصين","GlobalID":"d2a9035e-bfd4-4e5e-beb5-e015aeb7c7d4"},"geometry":{"x":103.89347310100004,"y":36.518701460000045}},{"attributes":{"OBJECTID":752,"ADM0_NAME":"CHINA","DateOfDataEntry":1580601600000,"cum_conf":14411,"NewCase":2590,"CENTER_LON":103.8934731,"CENTER_LAT":36.51870146,"ADM0_VIZ_NAME":"China","GUID":"af40da08-eeb3-40e9-bd59-41c06c17191f","Short_Name_ZH":"中国","Short_Name_FR":"Chine","Short_Name_ES":"China","Short_Name_RU":"Китай","Short_Name_AR":"الصين","GlobalID":"2e8ddf39-e7f6-4ad5-b635-f8ccd68c8190"},"geometry":{"x":103.89347310100004,"y":36.518701460000045}},{"attributes":{"OBJECTID":753,"ADM0_NAME":"CHINA","DateOfDataEntry":1580688000000,"cum_conf":17238,"NewCase":2827,"CENTER_LON":103.8934731,"CENTER_LAT":36.51870146,"ADM0_VIZ_NAME":"China","GUID":"af40da08-eeb3-40e9-bd59-41c06c17191f","Short_Name_ZH":"中国","Short_Name_FR":"Chine","Short_Name_ES":"China","Short_Name_RU":"Китай","Short_Name_AR":"الصين","GlobalID":"a0fbe7aa-f614-4dd3-8541-5a6c902b3621"},"geometry":{"x":103.89347310100004,"y":36.518701460000045}},{"attributes":{"OBJECTID":754,"ADM0_NAME":"CHINA","DateOfDataEntry":1580774400000,"cum_conf":20471,"NewCase":3233,"CENTER_LON":103.8934731,"CENTER_LAT":36.51870146,"ADM0_VIZ_NAME":"China","GUID":"af40da08-eeb3-40e9-bd59-41c06c17191f","Short_Name_ZH":"中国","Short_Name_FR":"Chine","Short_Name_ES":"China","Short_Name_RU":"Китай","Short_Name_AR":"الصين","GlobalID":"8d4b1fe6-2faf-4c31-a0b8-2b507b7ac8b6"},"geometry":{"x":103.89347310100004,"y":36.518701460000045}},{"attributes":{"OBJECTID":755,"ADM0_NAME":"CHINA","DateOfDataEntry":1580860800000,"cum_conf":24363,"NewCase":3892,"CENTER_LON":103.8934731,"CENTER_LAT":36.51870146,"ADM0_VIZ_NAME":"China","GUID":"af40da08-eeb3-40e9-bd59-41c06c17191f","Short_Name_ZH":"中国","Short_Name_FR":"Chine","Short_Name_ES":"China","Short_Name_RU":"Китай","Short_Name_AR":"الصين","GlobalID":"60dc78e9-da6d-494a-adae-f4bb47954f0d"},"geometry":{"x":103.89347310100004,"y":36.518701460000045}},{"attributes":{"OBJECTID":756,"ADM0_NAME":"CHINA","DateOfDataEntry":1580947200000,"cum_conf":28060,"NewCase":3697,"CENTER_LON":103.8934731,"CENTER_LAT":36.51870146,"ADM0_VIZ_NAME":"China","GUID":"af40da08-eeb3-40e9-bd59-41c06c17191f","Short_Name_ZH":"中国","Short_Name_FR":"Chine","Short_Name_ES":"China","Short_Name_RU":"Китай","Short_Name_AR":"الصين","GlobalID":"f19bb92e-c2d1-41b7-a058-e3a9825d0a24"},"geometry":{"x":103.89347310100004,"y":36.518701460000045}},{"attributes":{"OBJECTID":757,"ADM0_NAME":"CHINA","DateOfDataEntry":1581033600000,"cum_conf":31211,"NewCase":3151,"CENTER_LON":103.8934731,"CENTER_LAT":36.51870146,"ADM0_VIZ_NAME":"China","GUID":"af40da08-eeb3-40e9-bd59-41c06c17191f","Short_Name_ZH":"中国","Short_Name_FR":"Chine","Short_Name_ES":"China","Short_Name_RU":"Китай","Short_Name_AR":"الصين","GlobalID":"b5483471-22aa-40c2-82db-8a4e8ff6ec42"},"geometry":{"x":103.89347310100004,"y":36.518701460000045}},{"attributes":{"OBJECTID":758,"ADM0_NAME":"CHINA","DateOfDataEntry":1581120000000,"cum_conf":34598,"NewCase":3387,"CENTER_LON":103.8934731,"CENTER_LAT":36.51870146,"ADM0_VIZ_NAME":"China","GUID":"af40da08-eeb3-40e9-bd59-41c06c17191f","Short_Name_ZH":"中国","Short_Name_FR":"Chine","Short_Name_ES":"China","Short_Name_RU":"Китай","Short_Name_AR":"الصين","GlobalID":"d4373003-ac09-45b3-9f4e-f34ce333b0fd"},"geometry":{"x":103.89347310100004,"y":36.518701460000045}},{"attributes":{"OBJECTID":759,"ADM0_NAME":"CHINA","DateOfDataEntry":1581206400000,"cum_conf":37251,"NewCase":2653,"CENTER_LON":103.8934731,"CENTER_LAT":36.51870146,"ADM0_VIZ_NAME":"China","GUID":"af40da08-eeb3-40e9-bd59-41c06c17191f","Short_Name_ZH":"中国","Short_Name_FR":"Chine","Short_Name_ES":"China","Short_Name_RU":"Китай","Short_Name_AR":"الصين","GlobalID":"f9763b86-9349-4bec-8f55-6fcad3f53317"},"geometry":{"x":103.89347310100004,"y":36.518701460000045}},{"attributes":{"OBJECTID":760,"ADM0_NAME":"CHINA","DateOfDataEntry":1581292800000,"cum_conf":40235,"NewCase":2984,"CENTER_LON":103.8934731,"CENTER_LAT":36.51870146,"ADM0_VIZ_NAME":"China","GUID":"af40da08-eeb3-40e9-bd59-41c06c17191f","Short_Name_ZH":"中国","Short_Name_FR":"Chine","Short_Name_ES":"China","Short_Name_RU":"Китай","Short_Name_AR":"الصين","GlobalID":"a31bc01b-6b60-4772-8367-9cd10a653138"},"geometry":{"x":103.89347310100004,"y":36.518701460000045}},{"attributes":{"OBJECTID":761,"ADM0_NAME":"CHINA","DateOfDataEntry":1581379200000,"cum_conf":42708,"NewCase":2473,"CENTER_LON":103.8934731,"CENTER_LAT":36.51870146,"ADM0_VIZ_NAME":"China","GUID":"af40da08-eeb3-40e9-bd59-41c06c17191f","Short_Name_ZH":"中国","Short_Name_FR":"Chine","Short_Name_ES":"China","Short_Name_RU":"Китай","Short_Name_AR":"الصين","GlobalID":"8c6616e9-4386-4cca-bf02-7f8d907cbfa3"},"geometry":{"x":103.89347310100004,"y":36.518701460000045}},{"attributes":{"OBJECTID":762,"ADM0_NAME":"CHINA","DateOfDataEntry":1581465600000,"cum_conf":44730,"NewCase":2022,"CENTER_LON":103.8934731,"CENTER_LAT":36.51870146,"ADM0_VIZ_NAME":"China","GUID":"af40da08-eeb3-40e9-bd59-41c06c17191f","Short_Name_ZH":"中国","Short_Name_FR":"Chine","Short_Name_ES":"China","Short_Name_RU":"Китай","Short_Name_AR":"الصين","GlobalID":"84b8d7c7-a023-4ed7-b4e3-3c870aabb59e"},"geometry":{"x":103.89347310100004,"y":36.518701460000045}},{"attributes":{"OBJECTID":763,"ADM0_NAME":"CHINA","DateOfDataEntry":1581552000000,"cum_conf":59882,"NewCase":15152,"CENTER_LON":103.8934731,"CENTER_LAT":36.51870146,"ADM0_VIZ_NAME":"China","GUID":"af40da08-eeb3-40e9-bd59-41c06c17191f","Short_Name_ZH":"中国","Short_Name_FR":"Chine","Short_Name_ES":"China","Short_Name_RU":"Китай","Short_Name_AR":"الصين","GlobalID":"dc3a9a86-80b1-491d-9022-af5eb6d5569b"},"geometry":{"x":103.89347310100004,"y":36.518701460000045}},{"attributes":{"OBJECTID":764,"ADM0_NAME":"CHINA","DateOfDataEntry":1581638400000,"cum_conf":63932,"NewCase":4050,"CENTER_LON":103.8934731,"CENTER_LAT":36.51870146,"ADM0_VIZ_NAME":"China","GUID":"af40da08-eeb3-40e9-bd59-41c06c17191f","Short_Name_ZH":"中国","Short_Name_FR":"Chine","Short_Name_ES":"China","Short_Name_RU":"Китай","Short_Name_AR":"الصين","GlobalID":"0bbc2c74-ef2a-4501-a9d2-e24e0a35f6f4"},"geometry":{"x":103.89347310100004,"y":36.518701460000045}},{"attributes":{"OBJECTID":765,"ADM0_NAME":"CHINA","DateOfDataEntry":1581724800000,"cum_conf":66576,"NewCase":2644,"CENTER_LON":103.8934731,"CENTER_LAT":36.51870146,"ADM0_VIZ_NAME":"China","GUID":"af40da08-eeb3-40e9-bd59-41c06c17191f","Short_Name_ZH":"中国","Short_Name_FR":"Chine","Short_Name_ES":"China","Short_Name_RU":"Китай","Short_Name_AR":"الصين","GlobalID":"4741d144-49b2-421d-9e5e-d3a61ecf0e76"},"geometry":{"x":103.89347310100004,"y":36.518701460000045}},{"attributes":{"OBJECTID":766,"ADM0_NAME":"CHINA","DateOfDataEntry":1581811200000,"cum_conf":68584,"NewCase":2008,"CENTER_LON":103.8934731,"CENTER_LAT":36.51870146,"ADM0_VIZ_NAME":"China","GUID":"af40da08-eeb3-40e9-bd59-41c06c17191f","Short_Name_ZH":"中国","Short_Name_FR":"Chine","Short_Name_ES":"China","Short_Name_RU":"Китай","Short_Name_AR":"الصين","GlobalID":"9a05a81f-9f4f-45aa-9f4c-9c816b131faf"},"geometry":{"x":103.89347310100004,"y":36.518701460000045}},{"attributes":{"OBJECTID":767,"ADM0_NAME":"CHINA","DateOfDataEntry":1581897600000,"cum_conf":70635,"NewCase":2051,"CENTER_LON":103.8934731,"CENTER_LAT":36.51870146,"ADM0_VIZ_NAME":"China","GUID":"af40da08-eeb3-40e9-bd59-41c06c17191f","Short_Name_ZH":"中国","Short_Name_FR":"Chine","Short_Name_ES":"China","Short_Name_RU":"Китай","Short_Name_AR":"الصين","GlobalID":"b44448b1-59ba-4344-94bd-9a1a95172173"},"geometry":{"x":103.89347310100004,"y":36.518701460000045}},{"attributes":{"OBJECTID":768,"ADM0_NAME":"CHINA","DateOfDataEntry":1581984000000,"cum_conf":72528,"NewCase":1893,"CENTER_LON":103.8934731,"CENTER_LAT":36.51870146,"ADM0_VIZ_NAME":"China","GUID":"af40da08-eeb3-40e9-bd59-41c06c17191f","Short_Name_ZH":"中国","Short_Name_FR":"Chine","Short_Name_ES":"China","Short_Name_RU":"Китай","Short_Name_AR":"الصين","GlobalID":"fbd05e14-bb42-4c40-a4f7-69d87588447e"},"geometry":{"x":103.89347310100004,"y":36.518701460000045}},{"attributes":{"OBJECTID":769,"ADM0_NAME":"CHINA","DateOfDataEntry":1582070400000,"cum_conf":74279,"NewCase":1751,"CENTER_LON":103.8934731,"CENTER_LAT":36.51870146,"ADM0_VIZ_NAME":"China","GUID":"af40da08-eeb3-40e9-bd59-41c06c17191f","Short_Name_ZH":"中国","Short_Name_FR":"Chine","Short_Name_ES":"China","Short_Name_RU":"Китай","Short_Name_AR":"الصين","GlobalID":"0887e0b1-9f37-4654-9de3-eddf3a6a457e"},"geometry":{"x":103.89347310100004,"y":36.518701460000045}},{"attributes":{"OBJECTID":770,"ADM0_NAME":"CHINA","DateOfDataEntry":1582156800000,"cum_conf":74675,"NewCase":396,"CENTER_LON":103.8934731,"CENTER_LAT":36.51870146,"ADM0_VIZ_NAME":"China","GUID":"af40da08-eeb3-40e9-bd59-41c06c17191f","Short_Name_ZH":"中国","Short_Name_FR":"Chine","Short_Name_ES":"China","Short_Name_RU":"Китай","Short_Name_AR":"الصين","GlobalID":"47b645dc-e4dc-4327-a57e-538a7f894408"},"geometry":{"x":103.89347310100004,"y":36.518701460000045}},{"attributes":{"OBJECTID":771,"ADM0_NAME":"CHINA","DateOfDataEntry":1582243200000,"cum_conf":75567,"NewCase":892,"CENTER_LON":103.8934731,"CENTER_LAT":36.51870146,"ADM0_VIZ_NAME":"China","GUID":"af40da08-eeb3-40e9-bd59-41c06c17191f","Short_Name_ZH":"中国","Short_Name_FR":"Chine","Short_Name_ES":"China","Short_Name_RU":"Китай","Short_Name_AR":"الصين","GlobalID":"a604fdf4-8ece-4cb9-9ddc-10b45281a6f5"},"geometry":{"x":103.89347310100004,"y":36.518701460000045}},{"attributes":{"OBJECTID":772,"ADM0_NAME":"CHINA","DateOfDataEntry":1582329600000,"cum_conf":76392,"NewCase":825,"CENTER_LON":103.8934731,"CENTER_LAT":36.51870146,"ADM0_VIZ_NAME":"China","GUID":"af40da08-eeb3-40e9-bd59-41c06c17191f","Short_Name_ZH":"中国","Short_Name_FR":"Chine","Short_Name_ES":"China","Short_Name_RU":"Китай","Short_Name_AR":"الصين","GlobalID":"06e71140-37e2-41d2-91d7-fc1df33d1347"},"geometry":{"x":103.89347310100004,"y":36.518701460000045}},{"attributes":{"OBJECTID":773,"ADM0_NAME":"CHINA","DateOfDataEntry":1582416000000,"cum_conf":77041,"NewCase":649,"CENTER_LON":103.8934731,"CENTER_LAT":36.51870146,"ADM0_VIZ_NAME":"China","GUID":"af40da08-eeb3-40e9-bd59-41c06c17191f","Short_Name_ZH":"中国","Short_Name_FR":"Chine","Short_Name_ES":"China","Short_Name_RU":"Китай","Short_Name_AR":"الصين","GlobalID":"2024d902-2852-45c9-b5e5-44ef227b915f"},"geometry":{"x":103.89347310100004,"y":36.518701460000045}},{"attributes":{"OBJECTID":774,"ADM0_NAME":"CHINA","DateOfDataEntry":1582502400000,"cum_conf":77262,"NewCase":221,"CENTER_LON":103.8934731,"CENTER_LAT":36.51870146,"ADM0_VIZ_NAME":"China","GUID":"af40da08-eeb3-40e9-bd59-41c06c17191f","Short_Name_ZH":"中国","Short_Name_FR":"Chine","Short_Name_ES":"China","Short_Name_RU":"Китай","Short_Name_AR":"الصين","GlobalID":"4fcace19-16ea-47a7-ad5e-0d94df5dff05"},"geometry":{"x":103.89347310100004,"y":36.518701460000045}},{"attributes":{"OBJECTID":775,"ADM0_NAME":"CHINA","DateOfDataEntry":1582588800000,"cum_conf":77779,"NewCase":517,"CENTER_LON":103.8934731,"CENTER_LAT":36.51870146,"ADM0_VIZ_NAME":"China","GUID":"af40da08-eeb3-40e9-bd59-41c06c17191f","Short_Name_ZH":"中国","Short_Name_FR":"Chine","Short_Name_ES":"China","Short_Name_RU":"Китай","Short_Name_AR":"الصين","GlobalID":"de207d6d-454d-4f3b-bd40-233753668c6a"},"geometry":{"x":103.89347310100004,"y":36.518701460000045}},{"attributes":{"OBJECTID":776,"ADM0_NAME":"CHINA","DateOfDataEntry":1582675200000,"cum_conf":78191,"NewCase":412,"CENTER_LON":103.8934731,"CENTER_LAT":36.51870146,"ADM0_VIZ_NAME":"China","GUID":"af40da08-eeb3-40e9-bd59-41c06c17191f","Short_Name_ZH":"中国","Short_Name_FR":"Chine","Short_Name_ES":"China","Short_Name_RU":"Китай","Short_Name_AR":"الصين","GlobalID":"dca8ca63-06d0-41d9-8e4e-126053ac87d2"},"geometry":{"x":103.89347310100004,"y":36.518701460000045}},{"attributes":{"OBJECTID":777,"ADM0_NAME":"CHINA","DateOfDataEntry":1582761600000,"cum_conf":78630,"NewCase":439,"CENTER_LON":103.8934731,"CENTER_LAT":36.51870146,"ADM0_VIZ_NAME":"China","GUID":"af40da08-eeb3-40e9-bd59-41c06c17191f","Short_Name_ZH":"中国","Short_Name_FR":"Chine","Short_Name_ES":"China","Short_Name_RU":"Китай","Short_Name_AR":"الصين","GlobalID":"3ecdb421-997b-47d1-9cc5-1acf4cc107e5"},"geometry":{"x":103.89347310100004,"y":36.518701460000045}},{"attributes":{"OBJECTID":778,"ADM0_NAME":"CHINA","DateOfDataEntry":1582848000000,"cum_conf":78959,"NewCase":329,"CENTER_LON":103.8934731,"CENTER_LAT":36.51870146,"ADM0_VIZ_NAME":"China","GUID":"af40da08-eeb3-40e9-bd59-41c06c17191f","Short_Name_ZH":"中国","Short_Name_FR":"Chine","Short_Name_ES":"China","Short_Name_RU":"Китай","Short_Name_AR":"الصين","GlobalID":"8e39ad0e-c648-4b4c-a1cf-6086d2829e0b"},"geometry":{"x":103.89347310100004,"y":36.518701460000045}},{"attributes":{"OBJECTID":779,"ADM0_NAME":"CHINA","DateOfDataEntry":1582934400000,"cum_conf":79394,"NewCase":435,"CENTER_LON":103.8934731,"CENTER_LAT":36.51870146,"ADM0_VIZ_NAME":"China","GUID":"af40da08-eeb3-40e9-bd59-41c06c17191f","Short_Name_ZH":"中国","Short_Name_FR":"Chine","Short_Name_ES":"China","Short_Name_RU":"Китай","Short_Name_AR":"الصين","GlobalID":"27a0af2c-25ee-43dc-8e5a-d3841f177da1"},"geometry":{"x":103.89347310100004,"y":36.518701460000045}},{"attributes":{"OBJECTID":780,"ADM0_NAME":"CHINA","DateOfDataEntry":1583020800000,"cum_conf":79968,"NewCase":574,"CENTER_LON":103.8934731,"CENTER_LAT":36.51870146,"ADM0_VIZ_NAME":"China","GUID":"af40da08-eeb3-40e9-bd59-41c06c17191f","Short_Name_ZH":"中国","Short_Name_FR":"Chine","Short_Name_ES":"China","Short_Name_RU":"Китай","Short_Name_AR":"الصين","GlobalID":"14bedff1-2239-4918-96e5-287753efdf30"},"geometry":{"x":103.89347310100004,"y":36.518701460000045}},{"attributes":{"OBJECTID":781,"ADM0_NAME":"CHINA","DateOfDataEntry":1583107200000,"cum_conf":80174,"NewCase":206,"CENTER_LON":103.8934731,"CENTER_LAT":36.51870146,"ADM0_VIZ_NAME":"China","GUID":"af40da08-eeb3-40e9-bd59-41c06c17191f","Short_Name_ZH":"中国","Short_Name_FR":"Chine","Short_Name_ES":"China","Short_Name_RU":"Китай","Short_Name_AR":"الصين","GlobalID":"ddad885c-eb16-4ab4-a078-758f082bfa7c"},"geometry":{"x":103.89347310100004,"y":36.518701460000045}},{"attributes":{"OBJECTID":782,"ADM0_NAME":"CHINA","DateOfDataEntry":1583193600000,"cum_conf":80303,"NewCase":129,"CENTER_LON":103.8934731,"CENTER_LAT":36.51870146,"ADM0_VIZ_NAME":"China","GUID":"af40da08-eeb3-40e9-bd59-41c06c17191f","Short_Name_ZH":"中国","Short_Name_FR":"Chine","Short_Name_ES":"China","Short_Name_RU":"Китай","Short_Name_AR":"الصين","GlobalID":"db384a90-ed04-4226-9333-2842880b0a24"},"geometry":{"x":103.89347310100004,"y":36.518701460000045}},{"attributes":{"OBJECTID":783,"ADM0_NAME":"CHINA","DateOfDataEntry":1583280000000,"cum_conf":80422,"NewCase":119,"CENTER_LON":103.8934731,"CENTER_LAT":36.51870146,"ADM0_VIZ_NAME":"China","GUID":"af40da08-eeb3-40e9-bd59-41c06c17191f","Short_Name_ZH":"中国","Short_Name_FR":"Chine","Short_Name_ES":"China","Short_Name_RU":"Китай","Short_Name_AR":"الصين","GlobalID":"3ecf4d9d-829d-4c1f-9b8c-477bc731ed8a"},"geometry":{"x":103.89347310100004,"y":36.518701460000045}},{"attributes":{"OBJECTID":784,"ADM0_NAME":"CHINA","DateOfDataEntry":1583366400000,"cum_conf":80565,"NewCase":143,"CENTER_LON":103.8934731,"CENTER_LAT":36.51870146,"ADM0_VIZ_NAME":"China","GUID":"af40da08-eeb3-40e9-bd59-41c06c17191f","Short_Name_ZH":"中国","Short_Name_FR":"Chine","Short_Name_ES":"China","Short_Name_RU":"Китай","Short_Name_AR":"الصين","GlobalID":"e4cd1776-a6a3-44af-92e8-636f4352e03d"},"geometry":{"x":103.89347310100004,"y":36.518701460000045}},{"attributes":{"OBJECTID":785,"ADM0_NAME":"CHINA","DateOfDataEntry":1583452800000,"cum_conf":80710,"NewCase":145,"CENTER_LON":103.8934731,"CENTER_LAT":36.51870146,"ADM0_VIZ_NAME":"China","GUID":"af40da08-eeb3-40e9-bd59-41c06c17191f","Short_Name_ZH":"中国","Short_Name_FR":"Chine","Short_Name_ES":"China","Short_Name_RU":"Китай","Short_Name_AR":"الصين","GlobalID":"9ace1ac2-6694-4e9d-9995-bc406324990e"},"geometry":{"x":103.89347310100004,"y":36.518701460000045}},{"attributes":{"OBJECTID":786,"ADM0_NAME":"CHINA","DateOfDataEntry":1583539200000,"cum_conf":80813,"NewCase":103,"CENTER_LON":103.8934731,"CENTER_LAT":36.51870146,"ADM0_VIZ_NAME":"China","GUID":"af40da08-eeb3-40e9-bd59-41c06c17191f","Short_Name_ZH":"中国","Short_Name_FR":"Chine","Short_Name_ES":"China","Short_Name_RU":"Китай","Short_Name_AR":"الصين","GlobalID":"b2f677ef-4320-4b19-85b3-e515ae8e2398"},"geometry":{"x":103.89347310100004,"y":36.518701460000045}},{"attributes":{"OBJECTID":787,"ADM0_NAME":"CHINA","DateOfDataEntry":1583625600000,"cum_conf":80859,"NewCase":46,"CENTER_LON":103.8934731,"CENTER_LAT":36.51870146,"ADM0_VIZ_NAME":"China","GUID":"af40da08-eeb3-40e9-bd59-41c06c17191f","Short_Name_ZH":"中国","Short_Name_FR":"Chine","Short_Name_ES":"China","Short_Name_RU":"Китай","Short_Name_AR":"الصين","GlobalID":"df6b6ab6-3ee5-4c45-bdd3-c34912b0ff97"},"geometry":{"x":103.89347310100004,"y":36.518701460000045}},{"attributes":{"OBJECTID":788,"ADM0_NAME":"CHINA","DateOfDataEntry":1583712000000,"cum_conf":80904,"NewCase":45,"CENTER_LON":103.8934731,"CENTER_LAT":36.51870146,"ADM0_VIZ_NAME":"China","GUID":"af40da08-eeb3-40e9-bd59-41c06c17191f","Short_Name_ZH":"中国","Short_Name_FR":"Chine","Short_Name_ES":"China","Short_Name_RU":"Китай","Short_Name_AR":"الصين","GlobalID":"3c174937-c621-4b35-a055-7e6253e8b689"},"geometry":{"x":103.89347310100004,"y":36.518701460000045}},{"attributes":{"OBJECTID":789,"ADM0_NAME":"CHINA","DateOfDataEntry":1583798400000,"cum_conf":80924,"NewCase":20,"CENTER_LON":103.8934731,"CENTER_LAT":36.51870146,"ADM0_VIZ_NAME":"China","GUID":"af40da08-eeb3-40e9-bd59-41c06c17191f","Short_Name_ZH":"中国","Short_Name_FR":"Chine","Short_Name_ES":"China","Short_Name_RU":"Китай","Short_Name_AR":"الصين","GlobalID":"7ce74069-6a7b-4d88-965c-dfd8c0bf8dbc"},"geometry":{"x":103.89347310100004,"y":36.518701460000045}},{"attributes":{"OBJECTID":790,"ADM0_NAME":"CHINA","DateOfDataEntry":1583884800000,"cum_conf":80955,"NewCase":31,"CENTER_LON":103.8934731,"CENTER_LAT":36.51870146,"ADM0_VIZ_NAME":"China","GUID":"af40da08-eeb3-40e9-bd59-41c06c17191f","Short_Name_ZH":"中国","Short_Name_FR":"Chine","Short_Name_ES":"China","Short_Name_RU":"Китай","Short_Name_AR":"الصين","GlobalID":"519c5863-7e23-418e-afd6-dddaf5339308"},"geometry":{"x":103.89347310100004,"y":36.518701460000045}},{"attributes":{"OBJECTID":791,"ADM0_NAME":"CHINA","DateOfDataEntry":1583971200000,"cum_conf":80981,"NewCase":26,"CENTER_LON":103.8934731,"CENTER_LAT":36.51870146,"ADM0_VIZ_NAME":"China","GUID":"af40da08-eeb3-40e9-bd59-41c06c17191f","Short_Name_ZH":"中国","Short_Name_FR":"Chine","Short_Name_ES":"China","Short_Name_RU":"Китай","Short_Name_AR":"الصين","GlobalID":"10318285-5031-4a71-abee-cee473efd3c2"},"geometry":{"x":103.89347310100004,"y":36.518701460000045}},{"attributes":{"OBJECTID":792,"ADM0_NAME":"CHINA","DateOfDataEntry":1584057600000,"cum_conf":80981,"NewCase":0,"CENTER_LON":103.8934731,"CENTER_LAT":36.51870146,"ADM0_VIZ_NAME":"China","GUID":"af40da08-eeb3-40e9-bd59-41c06c17191f","Short_Name_ZH":"中国","Short_Name_FR":"Chine","Short_Name_ES":"China","Short_Name_RU":"Китай","Short_Name_AR":"الصين","GlobalID":"fea1dc75-4e9d-48e1-b12d-18bd767baa5b"},"geometry":{"x":103.89347310100004,"y":36.518701460000045}},{"attributes":{"OBJECTID":793,"ADM0_NAME":"CHINA","DateOfDataEntry":1584144000000,"cum_conf":81021,"NewCase":40,"CENTER_LON":103.8934731,"CENTER_LAT":36.51870146,"ADM0_VIZ_NAME":"China","GUID":"af40da08-eeb3-40e9-bd59-41c06c17191f","Short_Name_ZH":"中国","Short_Name_FR":"Chine","Short_Name_ES":"China","Short_Name_RU":"Китай","Short_Name_AR":"الصين","GlobalID":"c908a13a-889d-4bab-afde-9d382dead5b0"},"geometry":{"x":103.89347310100004,"y":36.518701460000045}},{"attributes":{"OBJECTID":794,"ADM0_NAME":"CHINA","DateOfDataEntry":1584230400000,"cum_conf":81048,"NewCase":27,"CENTER_LON":103.8934731,"CENTER_LAT":36.51870146,"ADM0_VIZ_NAME":"China","GUID":"af40da08-eeb3-40e9-bd59-41c06c17191f","Short_Name_ZH":"中国","Short_Name_FR":"Chine","Short_Name_ES":"China","Short_Name_RU":"Китай","Short_Name_AR":"الصين","GlobalID":"4305e62b-9b13-4874-8a99-1ab7ae5e003c"},"geometry":{"x":103.89347310100004,"y":36.518701460000045}},{"attributes":{"OBJECTID":795,"ADM0_NAME":"China","DateOfDataEntry":1584316800000,"cum_conf":81077,"NewCase":29,"CENTER_LON":103.8934731,"CENTER_LAT":36.51870146,"ADM0_VIZ_NAME":"China","GUID":"af40da08-eeb3-40e9-bd59-41c06c17191f","Short_Name_ZH":"中国","Short_Name_FR":"Chine","Short_Name_ES":"China","Short_Name_RU":"Китай","Short_Name_AR":"الصين","GlobalID":"2ed6ebbc-cd34-4e7a-9de7-5c07f3b3acdd"},"geometry":{"x":103.89347310100004,"y":36.518701460000045}},{"attributes":{"OBJECTID":796,"ADM0_NAME":"China","DateOfDataEntry":1584403200000,"cum_conf":82007,"NewCase":930,"CENTER_LON":103.8934731,"CENTER_LAT":36.51870146,"ADM0_VIZ_NAME":"China","GUID":"af40da08-eeb3-40e9-bd59-41c06c17191f","Short_Name_ZH":"中国","Short_Name_FR":"Chine","Short_Name_ES":"China","Short_Name_RU":"Китай","Short_Name_AR":"الصين","GlobalID":"51434ebd-b816-4a46-bcf6-37f783f9b843"},"geometry":{"x":103.89347310100004,"y":36.518701460000045}},{"attributes":{"OBJECTID":797,"ADM0_NAME":"China","DateOfDataEntry":1584489600000,"cum_conf":81174,"NewCase":-833,"CENTER_LON":103.8934731,"CENTER_LAT":36.51870146,"ADM0_VIZ_NAME":"China","GUID":"af40da08-eeb3-40e9-bd59-41c06c17191f","Short_Name_ZH":"中国","Short_Name_FR":"Chine","Short_Name_ES":"China","Short_Name_RU":"Китай","Short_Name_AR":"الصين","GlobalID":"95625288-0254-4cc8-b139-57f0de652a4f"},"geometry":{"x":103.89347310100004,"y":36.518701460000045}},{"attributes":{"OBJECTID":798,"ADM0_NAME":"China","DateOfDataEntry":1584576000000,"cum_conf":81174,"NewCase":0,"CENTER_LON":103.8934731,"CENTER_LAT":36.51870146,"ADM0_VIZ_NAME":"China","GUID":"af40da08-eeb3-40e9-bd59-41c06c17191f","Short_Name_ZH":"中国","Short_Name_FR":"Chine","Short_Name_ES":"China","Short_Name_RU":"Китай","Short_Name_AR":"الصين","GlobalID":"0dfa832b-512f-4cab-b71c-0afcdf3a4710"},"geometry":{"x":103.89347310100004,"y":36.518701460000045}},{"attributes":{"OBJECTID":799,"ADM0_NAME":"China","DateOfDataEntry":1584662400000,"cum_conf":81300,"NewCase":126,"CENTER_LON":103.8934731,"CENTER_LAT":36.51870146,"ADM0_VIZ_NAME":"China","GUID":"af40da08-eeb3-40e9-bd59-41c06c17191f","Short_Name_ZH":"中国","Short_Name_FR":"Chine","Short_Name_ES":"China","Short_Name_RU":"Китай","Short_Name_AR":"الصين","GlobalID":"0615a598-5021-458a-baf6-99522cae4081"},"geometry":{"x":103.89347310100004,"y":36.518701460000045}},{"attributes":{"OBJECTID":800,"ADM0_NAME":"China","DateOfDataEntry":1584748800000,"cum_conf":81416,"NewCase":116,"CENTER_LON":103.8934731,"CENTER_LAT":36.51870146,"ADM0_VIZ_NAME":"China","GUID":"af40da08-eeb3-40e9-bd59-41c06c17191f","Short_Name_ZH":"中国","Short_Name_FR":"Chine","Short_Name_ES":"China","Short_Name_RU":"Китай","Short_Name_AR":"الصين","GlobalID":"d8872163-4f09-48f2-ba4c-c263ddcd82eb"},"geometry":{"x":103.89347310100004,"y":36.518701460000045}},{"attributes":{"OBJECTID":801,"ADM0_NAME":"China","DateOfDataEntry":1584835200000,"cum_conf":81499,"NewCase":83,"CENTER_LON":103.8934731,"CENTER_LAT":36.51870146,"ADM0_VIZ_NAME":"China","GUID":"af40da08-eeb3-40e9-bd59-41c06c17191f","Short_Name_ZH":"中国","Short_Name_FR":"Chine","Short_Name_ES":"China","Short_Name_RU":"Китай","Short_Name_AR":"الصين","GlobalID":"1ed39f46-0ea5-499a-a0b2-0828c98f3816"},"geometry":{"x":103.89347310100004,"y":36.518701460000045}},{"attributes":{"OBJECTID":802,"ADM0_NAME":"China","DateOfDataEntry":1584921600000,"cum_conf":81603,"NewCase":104,"CENTER_LON":103.8934731,"CENTER_LAT":36.51870146,"ADM0_VIZ_NAME":"China","GUID":"af40da08-eeb3-40e9-bd59-41c06c17191f","Short_Name_ZH":"中国","Short_Name_FR":"Chine","Short_Name_ES":"China","Short_Name_RU":"Китай","Short_Name_AR":"الصين","GlobalID":"88727dd0-18a8-4b4e-8132-0edc4d618e92"},"geometry":{"x":103.89347310100004,"y":36.518701460000045}},{"attributes":{"OBJECTID":803,"ADM0_NAME":"China","DateOfDataEntry":1585008000000,"cum_conf":81767,"NewCase":164,"CENTER_LON":103.8934731,"CENTER_LAT":36.51870146,"ADM0_VIZ_NAME":"China","GUID":"af40da08-eeb3-40e9-bd59-41c06c17191f","Short_Name_ZH":"中国","Short_Name_FR":"Chine","Short_Name_ES":"China","Short_Name_RU":"Китай","Short_Name_AR":"الصين","GlobalID":"c2f53763-9646-44fa-8afb-97e3ea9a373d"},"geometry":{"x":103.89347310100004,"y":36.518701460000045}}]}
