{"objectIdFieldName":"OBJECTID","uniqueIdField":{"name":"OBJECTID","isSystemMaintained":true},"globalIdFieldName":"GlobalID","geometryType":"esriGeometryPoint","spatialReference":{"wkid":4326,"latestWkid":4326},"fields":[{"name":"OBJECTID","type":"esriFieldTypeOID","alias":"OBJECTID","sqlType":"sqlTypeOther","domain":null,"defaultValue":null},{"name":"ADM0_NAME","type":"esriFieldTypeString","alias":"ADM0_NAME","sqlType":"sqlTypeOther","length":255,"domain":null,"defaultValue":null},{"name":"DateOfDataEntry","type":"esriFieldTypeDate","alias":"DateOfDataEntry","sqlType":"sqlTypeOther","length":8,"domain":null,"defaultValue":null},{"name":"cum_conf","type":"esriFieldTypeInteger","alias":"cum_conf","sqlType":"sqlTypeOther","domain":null,"defaultValue":null},{"name":"NewCase","type":"esriFieldTypeInteger","alias":"NewCase","sqlType":"sqlTypeOther","domain":null,"defaultValue":null},{"name":"CENTER_LON","type":"esriFieldTypeDouble","alias":"CENTER_LON","sqlType":"sqlTypeOther","domain":null,"defaultValue":null},{"name":"CENTER_LAT","type":"esriFieldTypeDouble","alias":"CENTER_LAT","sqlType":"sqlTypeOther","domain":null,"defaultValue":null},{"name":"ADM0_VIZ_NAME","type":"esriFieldTypeString","alias":"ADM0_VIZ_NAME","sqlType":"sqlTypeOther","length":255,"domain":null,"defaultValue":null},{"name":"GUID","type":"esriFieldTypeGUID","alias":"GUID","sqlType":"sqlTypeOther","length":38,"domain":null,"defaultValue":null},{"name":"Short_Name_ZH","type":"esriFieldTypeString","alias":"Short_Name_ZH","sqlType":"sqlTypeOther","length":255,"domain":null,"defaultValue":null},{"name":"Short_Name_FR","type":"esriFieldTypeString","alias":"Short_Name_FR","sqlType":"sqlTypeOther","length":255,"domain":null,"defaultValue":null},{"name":"Short_Name_ES","type":"esriFieldTypeString","alias":"Short_Name_ES","sqlType":"sqlTypeOther","length":255,"domain":null,"defaultValue":null},{"name":"Short_Name_RU","type":"esriFieldTypeString","alias":"Short_Name_RU","sqlType":"sqlTypeOther","length":255,"domain":null,"defaultValue":null},{"name":"Short_Name_AR","type":"esriFieldTypeString","alias":"Short_Name_AR","sqlType":"sqlTypeOther","length":255,"domain":null,"defaultValue":null},{"name":"GlobalID","type":"esriFieldTypeGlobalID","alias":"GlobalID","sqlType":"sqlTypeOther","length":38,"domain":null,"defaultValue":null}],"features":[{"attributes":{"OBJECTID":2384,"ADM0_NAME":"NORTH MACEDONIA","DateOfDataEntry":1582761600000,"cum_conf":1,"NewCase":1,"CENTER_LON":21.6991485,"CENTER_LAT":41.59922075,"ADM0_VIZ_NAME":"North Macedonia","GUID":"3e3320e9-1f0d-44fb-9ca7-59fcb032f585","Short_Name_ZH":"北马其顿","Short_Name_FR":"Macédoine du Nord","Short_Name_ES":"Macedonia del Norte","Short_Name_RU":"Северная Македония","Short_Name_AR":"مقدونيا الشمالية","GlobalID":"8e07fde8-0222-48a2-8554-da06a2783abe"},"geometry":{"x":21.699148501000025,"y":41.599220753000054}},{"attributes":{"OBJECTID":2385,"ADM0_NAME":"NORTH MACEDONIA","DateOfDataEntry":1582848000000,"cum_conf":1,"NewCase":0,"CENTER_LON":21.6991485,"CENTER_LAT":41.59922075,"ADM0_VIZ_NAME":"North Macedonia","GUID":"3e3320e9-1f0d-44fb-9ca7-59fcb032f585","Short_Name_ZH":"北马其顿","Short_Name_FR":"Macédoine du Nord","Short_Name_ES":"Macedonia del Norte","Short_Name_RU":"Северная Македония","Short_Name_AR":"مقدونيا الشمالية","GlobalID":"9035c91f-a22a-4c1f-9cc8-33a53b224847"},"geometry":{"x":21.699148501000025,"y":41.599220753000054}},{"attributes":{"OBJECTID":2386,"ADM0_NAME":"NORTH MACEDONIA","DateOfDataEntry":1582934400000,"cum_conf":1,"NewCase":0,"CENTER_LON":21.6991485,"CENTER_LAT":41.59922075,"ADM0_VIZ_NAME":"North Macedonia","GUID":"3e3320e9-1f0d-44fb-9ca7-59fcb032f585","Short_Name_ZH":"北马其顿","Short_Name_FR":"Macédoine du Nord","Short_Name_ES":"Macedonia del Norte","Short_Name_RU":"Северная Македония","Short_Name_AR":"مقدونيا الشمالية","GlobalID":"cafb9dc4-f898-45da-8154-b8a0dbf30ae3"},"geometry":{"x":21.699148501000025,"y":41.599220753000054}},{"attributes":{"OBJECTID":2387,"ADM0_NAME":"NORTH MACEDONIA","DateOfDataEntry":1583020800000,"cum_conf":1,"NewCase":0,"CENTER_LON":21.6991485,"CENTER_LAT":41.59922075,"ADM0_VIZ_NAME":"North Macedonia","GUID":"3e3320e9-1f0d-44fb-9ca7-59fcb032f585","Short_Name_ZH":"北马其顿","Short_Name_FR":"Macédoine du Nord","Short_Name_ES":"Macedonia del Norte","Short_Name_RU":"Северная Македония","Short_Name_AR":"مقدونيا الشمالية","GlobalID":"19bfd5db-46b3-4f89-a3c7-e35e12879998"},"geometry":{"x":21.699148501000025,"y":41.599220753000054}},{"attributes":{"OBJECTID":2388,"ADM0_NAME":"NORTH MACEDONIA","DateOfDataEntry":1583107200000,"cum_conf":1,"NewCase":0,"CENTER_LON":21.6991485,"CENTER_LAT":41.59922075,"ADM0_VIZ_NAME":"North Macedonia","GUID":"3e3320e9-1f0d-44fb-9ca7-59fcb032f585","Short_Name_ZH":"北马其顿","Short_Name_FR":"Macédoine du Nord","Short_Name_ES":"Macedonia del Norte","Short_Name_RU":"Северная Македония","Short_Name_AR":"مقدونيا الشمالية","GlobalID":"159b5fdb-b705-4e1f-b568-48dab53cc351"},"geometry":{"x":21.699148501000025,"y":41.599220753000054}},{"attributes":{"OBJECTID":2389,"ADM0_NAME":"NORTH MACEDONIA","DateOfDataEntry":1583193600000,"cum_conf":1,"NewCase":0,"CENTER_LON":21.6991485,"CENTER_LAT":41.59922075,"ADM0_VIZ_NAME":"North Macedonia","GUID":"3e3320e9-1f0d-44fb-9ca7-59fcb032f585","Short_Name_ZH":"北马其顿","Short_Name_FR":"Macédoine du Nord","Short_Name_ES":"Macedonia del Norte","Short_Name_RU":"Северная Македония","Short_Name_AR":"مقدونيا الشمالية","GlobalID":"a39f75ef-3456-4f9f-955b-d92a26d9d768"},"geometry":{"x":21.699148501000025,"y":41.599220753000054}},{"attributes":{"OBJECTID":2390,"ADM0_NAME":"NORTH MACEDONIA","DateOfDataEntry":1583280000000,"cum_conf":1,"NewCase":0,"CENTER_LON":21.6991485,"CENTER_LAT":41.59922075,"ADM0_VIZ_NAME":"North Macedonia","GUID":"3e3320e9-1f0d-44fb-9ca7-59fcb032f585","Short_Name_ZH":"北马其顿","Short_Name_FR":"Macédoine du Nord","Short_Name_ES":"Macedonia del Norte","Short_Name_RU":"Северная Македония","Short_Name_AR":"مقدونيا الشمالية","GlobalID":"e816e90d-480d-4d1b-9c0b-1db1adfb2794"},"geometry":{"x":21.699148501000025,"y":41.599220753000054}},{"attributes":{"OBJECTID":2391,"ADM0_NAME":"NORTH MACEDONIA","DateOfDataEntry":1583366400000,"cum_conf":1,"NewCase":0,"CENTER_LON":21.6991485,"CENTER_LAT":41.59922075,"ADM0_VIZ_NAME":"North Macedonia","GUID":"3e3320e9-1f0d-44fb-9ca7-59fcb032f585","Short_Name_ZH":"北马其顿","Short_Name_FR":"Macédoine du Nord","Short_Name_ES":"Macedonia del Norte","Short_Name_RU":"Северная Македония","Short_Name_AR":"مقدونيا الشمالية","GlobalID":"256bfebc-68f9-4f85-a5ec-8689803e11d6"},"geometry":{"x":21.699148501000025,"y":41.599220753000054}},{"attributes":{"OBJECTID":2392,"ADM0_NAME":"NORTH MACEDONIA","DateOfDataEntry":1583452800000,"cum_conf":1,"NewCase":0,"CENTER_LON":21.6991485,"CENTER_LAT":41.59922075,"ADM0_VIZ_NAME":"North Macedonia","GUID":"3e3320e9-1f0d-44fb-9ca7-59fcb032f585","Short_Name_ZH":"北马其顿","Short_Name_FR":"Macédoine du Nord","Short_Name_ES":"Macedonia del Norte","Short_Name_RU":"Северная Македония","Short_Name_AR":"مقدونيا الشمالية","GlobalID":"b7c6755a-1278-422d-be1c-aff39de8d85e"},"geometry":{"x":21.699148501000025,"y":41.599220753000054}},{"attributes":{"OBJECTID":2393,"ADM0_NAME":"NORTH MACEDONIA","DateOfDataEntry":1583539200000,"cum_conf":3,"NewCase":2,"CENTER_LON":21.6991485,"CENTER_LAT":41.59922075,"ADM0_VIZ_NAME":"North Macedonia","GUID":"3e3320e9-1f0d-44fb-9ca7-59fcb032f585","Short_Name_ZH":"北马其顿","Short_Name_FR":"Macédoine du Nord","Short_Name_ES":"Macedonia del Norte","Short_Name_RU":"Северная Македония","Short_Name_AR":"مقدونيا الشمالية","GlobalID":"55bcc290-4cb6-4f40-8d57-28652502e5bf"},"geometry":{"x":21.699148501000025,"y":41.599220753000054}},{"attributes":{"OBJECTID":2394,"ADM0_NAME":"NORTH MACEDONIA","DateOfDataEntry":1583625600000,"cum_conf":3,"NewCase":0,"CENTER_LON":21.6991485,"CENTER_LAT":41.59922075,"ADM0_VIZ_NAME":"North Macedonia","GUID":"3e3320e9-1f0d-44fb-9ca7-59fcb032f585","Short_Name_ZH":"北马其顿","Short_Name_FR":"Macédoine du Nord","Short_Name_ES":"Macedonia del Norte","Short_Name_RU":"Северная Македония","Short_Name_AR":"مقدونيا الشمالية","GlobalID":"5876d8c2-a9a0-4b69-8118-4925e837cc73"},"geometry":{"x":21.699148501000025,"y":41.599220753000054}},{"attributes":{"OBJECTID":2395,"ADM0_NAME":"NORTH MACEDONIA","DateOfDataEntry":1583712000000,"cum_conf":4,"NewCase":1,"CENTER_LON":21.6991485,"CENTER_LAT":41.59922075,"ADM0_VIZ_NAME":"North Macedonia","GUID":"3e3320e9-1f0d-44fb-9ca7-59fcb032f585","Short_Name_ZH":"北马其顿","Short_Name_FR":"Macédoine du Nord","Short_Name_ES":"Macedonia del Norte","Short_Name_RU":"Северная Македония","Short_Name_AR":"مقدونيا الشمالية","GlobalID":"85cdbe11-ab8d-494b-b0d9-98c18b434308"},"geometry":{"x":21.699148501000025,"y":41.599220753000054}},{"attributes":{"OBJECTID":2396,"ADM0_NAME":"NORTH MACEDONIA","DateOfDataEntry":1583798400000,"cum_conf":7,"NewCase":3,"CENTER_LON":21.6991485,"CENTER_LAT":41.59922075,"ADM0_VIZ_NAME":"North Macedonia","GUID":"3e3320e9-1f0d-44fb-9ca7-59fcb032f585","Short_Name_ZH":"北马其顿","Short_Name_FR":"Macédoine du Nord","Short_Name_ES":"Macedonia del Norte","Short_Name_RU":"Северная Македония","Short_Name_AR":"مقدونيا الشمالية","GlobalID":"b0592a54-051b-4cc0-857a-509050c67984"},"geometry":{"x":21.699148501000025,"y":41.599220753000054}},{"attributes":{"OBJECTID":2397,"ADM0_NAME":"NORTH MACEDONIA","DateOfDataEntry":1583884800000,"cum_conf":7,"NewCase":0,"CENTER_LON":21.6991485,"CENTER_LAT":41.59922075,"ADM0_VIZ_NAME":"North Macedonia","GUID":"3e3320e9-1f0d-44fb-9ca7-59fcb032f585","Short_Name_ZH":"北马其顿","Short_Name_FR":"Macédoine du Nord","Short_Name_ES":"Macedonia del Norte","Short_Name_RU":"Северная Македония","Short_Name_AR":"مقدونيا الشمالية","GlobalID":"b6ab721e-0537-4a01-ba24-16eb853da8fa"},"geometry":{"x":21.699148501000025,"y":41.599220753000054}},{"attributes":{"OBJECTID":2398,"ADM0_NAME":"NORTH MACEDONIA","DateOfDataEntry":1583971200000,"cum_conf":7,"NewCase":0,"CENTER_LON":21.6991485,"CENTER_LAT":41.59922075,"ADM0_VIZ_NAME":"North Macedonia","GUID":"3e3320e9-1f0d-44fb-9ca7-59fcb032f585","Short_Name_ZH":"北马其顿","Short_Name_FR":"Macédoine du Nord","Short_Name_ES":"Macedonia del Norte","Short_Name_RU":"Северная Македония","Short_Name_AR":"مقدونيا الشمالية","GlobalID":"b20070e6-9132-4ba0-8ad8-dab7a7794d0e"},"geometry":{"x":21.699148501000025,"y":41.599220753000054}},{"attributes":{"OBJECTID":2399,"ADM0_NAME":"NORTH MACEDONIA","DateOfDataEntry":1584057600000,"cum_conf":9,"NewCase":2,"CENTER_LON":21.6991485,"CENTER_LAT":41.59922075,"ADM0_VIZ_NAME":"North Macedonia","GUID":"3e3320e9-1f0d-44fb-9ca7-59fcb032f585","Short_Name_ZH":"北马其顿","Short_Name_FR":"Macédoine du Nord","Short_Name_ES":"Macedonia del Norte","Short_Name_RU":"Северная Македония","Short_Name_AR":"مقدونيا الشمالية","GlobalID":"32fcb432-dc28-4a38-ad40-8c4a351b42b2"},"geometry":{"x":21.699148501000025,"y":41.599220753000054}},{"attributes":{"OBJECTID":2400,"ADM0_NAME":"NORTH MACEDONIA","DateOfDataEntry":1584144000000,"cum_conf":13,"NewCase":4,"CENTER_LON":21.6991485,"CENTER_LAT":41.59922075,"ADM0_VIZ_NAME":"North Macedonia","GUID":"3e3320e9-1f0d-44fb-9ca7-59fcb032f585","Short_Name_ZH":"北马其顿","Short_Name_FR":"Macédoine du Nord","Short_Name_ES":"Macedonia del Norte","Short_Name_RU":"Северная Македония","Short_Name_AR":"مقدونيا الشمالية","GlobalID":"a3f53720-10b5-4ce2-adec-c16917e27507"},"geometry":{"x":21.699148501000025,"y":41.599220753000054}},{"attributes":{"OBJECTID":2401,"ADM0_NAME":"NORTH MACEDONIA","DateOfDataEntry":1584230400000,"cum_conf":13,"NewCase":0,"CENTER_LON":21.6991485,"CENTER_LAT":41.59922075,"ADM0_VIZ_NAME":"North Macedonia","GUID":"3e3320e9-1f0d-44fb-9ca7-59fcb032f585","Short_Name_ZH":"北马其顿","Short_Name_FR":"Macédoine du Nord","Short_Name_ES":"Macedonia del Norte","Short_Name_RU":"Северная Македония","Short_Name_AR":"مقدونيا الشمالية","GlobalID":"e7f761e9-14d2-4f22-afca-2f824a6fcab1"},"geometry":{"x":21.699148501000025,"y":41.599220753000054}},{"attributes":{"OBJECTID":2402,"ADM0_NAME":"North Macedonia","DateOfDataEntry":1584316800000,"cum_conf":13,"NewCase":0,"CENTER_LON":21.6991485,"CENTER_LAT":41.59922075,"ADM0_VIZ_NAME":"North Macedonia","GUID":"3e3320e9-1f0d-44fb-9ca7-59fcb032f585","Short_Name_ZH":"北马其顿","Short_Name_FR":"Macédoine du Nord","Short_Name_ES":"Macedonia del Norte","Short_Name_RU":"Северная Македония","Short_Name_AR":"مقدونيا الشمالية","GlobalID":"f9ce4737-b1b9-4070-9f37-dd99b8a827b7"},"geometry":{"x":21.699148501000025,"y":41.599220753000054}},{"attributes":{"OBJECTID":2403,"ADM0_NAME":"North Macedonia","DateOfDataEntry":1584403200000,"cum_conf":26,"NewCase":13,"CENTER_LON":21.6991485,"CENTER_LAT":41.59922075,"ADM0_VIZ_NAME":"North Macedonia","GUID":"3e3320e9-1f0d-44fb-9ca7-59fcb032f585","Short_Name_ZH":"北马其顿","Short_Name_FR":"Macédoine du Nord","Short_Name_ES":"Macedonia del Norte","Short_Name_RU":"Северная Македония","Short_Name_AR":"مقدونيا الشمالية","GlobalID":"4af2b146-e400-4d2b-b388-f00cd3e200aa"},"geometry":{"x":21.699148501000025,"y":41.599220753000054}},{"attributes":{"OBJECTID":2404,"ADM0_NAME":"North Macedonia","DateOfDataEntry":1584489600000,"cum_conf":36,"NewCase":10,"CENTER_LON":21.6991485,"CENTER_LAT":41.59922075,"ADM0_VIZ_NAME":"North Macedonia","GUID":"3e3320e9-1f0d-44fb-9ca7-59fcb032f585","Short_Name_ZH":"北马其顿","Short_Name_FR":"Macédoine du Nord","Short_Name_ES":"Macedonia del Norte","Short_Name_RU":"Северная Македония","Short_Name_AR":"مقدونيا الشمالية","GlobalID":"8ce09f67-886b-43b8-914c-1eda978592e5"},"geometry":{"x":21.699148501000025,"y":41.599220753000054}},{"attributes":{"OBJECTID":2405,"ADM0_NAME":"North Macedonia","DateOfDataEntry":1584576000000,"cum_conf":36,"NewCase":0,"CENTER_LON":21.6991485,"CENTER_LAT":41.59922075,"ADM0_VIZ_NAME":"North Macedonia","GUID":"3e3320e9-1f0d-44fb-9ca7-59fcb032f585","Short_Name_ZH":"北马其顿","Short_Name_FR":"Macédoine du Nord","Short_Name_ES":"Macedonia del Norte","Short_Name_RU":"Северная Македония","Short_Name_AR":"مقدونيا الشمالية","GlobalID":"06bf75ac-e1ce-4235-b50e-c1e34f2d33b9"},"geometry":{"x":21.699148501000025,"y":41.599220753000054}},{"attributes":{"OBJECTID":2406,"ADM0_NAME":"North Macedonia","DateOfDataEntry":1584662400000,"cum_conf":48,"NewCase":12,"CENTER_LON":21.6991485,"CENTER_LAT":41.59922075,"ADM0_VIZ_NAME":"North Macedonia","GUID":"3e3320e9-1f0d-44fb-9ca7-59fcb032f585","Short_Name_ZH":"北马其顿","Short_Name_FR":"Macédoine du Nord","Short_Name_ES":"Macedonia del Norte","Short_Name_RU":"Северная Македония","Short_Name_AR":"مقدونيا الشمالية","GlobalID":"9ed8d32e-8893-4213-a2ea-ec9cea654a63"},"geometry":{"x":21.699148501000025,"y":41.599220753000054}},{"attributes":{"OBJECTID":2407,"ADM0_NAME":"North Macedonia","DateOfDataEntry":1584748800000,"cum_conf":70,"NewCase":22,"CENTER_LON":21.6991485,"CENTER_LAT":41.59922075,"ADM0_VIZ_NAME":"North Macedonia","GUID":"3e3320e9-1f0d-44fb-9ca7-59fcb032f585","Short_Name_ZH":"北马其顿","Short_Name_FR":"Macédoine du Nord","Short_Name_ES":"Macedonia del Norte","Short_Name_RU":"Северная Македония","Short_Name_AR":"مقدونيا الشمالية","GlobalID":"1e70e81b-f848-41fc-aeed-96fb7d9eb293"},"geometry":{"x":21.699148501000025,"y":41.599220753000054}},{"attributes":{"OBJECTID":2408,"ADM0_NAME":"North Macedonia","DateOfDataEntry":1584835200000,"cum_conf":85,"NewCase":15,"CENTER_LON":21.6991485,"CENTER_LAT":41.59922075,"ADM0_VIZ_NAME":"North Macedonia","GUID":"3e3320e9-1f0d-44fb-9ca7-59fcb032f585","Short_Name_ZH":"北马其顿","Short_Name_FR":"Macédoine du Nord","Short_Name_ES":"Macedonia del Norte","Short_Name_RU":"Северная Македония","Short_Name_AR":"مقدونيا الشمالية","GlobalID":"e829d057-4e48-407b-8197-26bc380a3be1"},"geometry":{"x":21.699148501000025,"y":41.599220753000054}}]}
