{"objectIdFieldName":"OBJECTID","uniqueIdField":{"name":"OBJECTID","isSystemMaintained":true},"globalIdFieldName":"GlobalID","geometryType":"esriGeometryPoint","spatialReference":{"wkid":4326,"latestWkid":4326},"fields":[{"name":"OBJECTID","type":"esriFieldTypeOID","alias":"OBJECTID","sqlType":"sqlTypeOther","domain":null,"defaultValue":null},{"name":"ADM0_NAME","type":"esriFieldTypeString","alias":"ADM0_NAME","sqlType":"sqlTypeOther","length":255,"domain":null,"defaultValue":null},{"name":"DateOfDataEntry","type":"esriFieldTypeDate","alias":"DateOfDataEntry","sqlType":"sqlTypeOther","length":8,"domain":null,"defaultValue":null},{"name":"cum_conf","type":"esriFieldTypeInteger","alias":"cum_conf","sqlType":"sqlTypeOther","domain":null,"defaultValue":null},{"name":"NewCase","type":"esriFieldTypeInteger","alias":"NewCase","sqlType":"sqlTypeOther","domain":null,"defaultValue":null},{"name":"CENTER_LON","type":"esriFieldTypeDouble","alias":"CENTER_LON","sqlType":"sqlTypeOther","domain":null,"defaultValue":null},{"name":"CENTER_LAT","type":"esriFieldTypeDouble","alias":"CENTER_LAT","sqlType":"sqlTypeOther","domain":null,"defaultValue":null},{"name":"ADM0_VIZ_NAME","type":"esriFieldTypeString","alias":"ADM0_VIZ_NAME","sqlType":"sqlTypeOther","length":255,"domain":null,"defaultValue":null},{"name":"GUID","type":"esriFieldTypeGUID","alias":"GUID","sqlType":"sqlTypeOther","length":38,"domain":null,"defaultValue":null},{"name":"Short_Name_ZH","type":"esriFieldTypeString","alias":"Short_Name_ZH","sqlType":"sqlTypeOther","length":255,"domain":null,"defaultValue":null},{"name":"Short_Name_FR","type":"esriFieldTypeString","alias":"Short_Name_FR","sqlType":"sqlTypeOther","length":255,"domain":null,"defaultValue":null},{"name":"Short_Name_ES","type":"esriFieldTypeString","alias":"Short_Name_ES","sqlType":"sqlTypeOther","length":255,"domain":null,"defaultValue":null},{"name":"Short_Name_RU","type":"esriFieldTypeString","alias":"Short_Name_RU","sqlType":"sqlTypeOther","length":255,"domain":null,"defaultValue":null},{"name":"Short_Name_AR","type":"esriFieldTypeString","alias":"Short_Name_AR","sqlType":"sqlTypeOther","length":255,"domain":null,"defaultValue":null},{"name":"GlobalID","type":"esriFieldTypeGlobalID","alias":"GlobalID","sqlType":"sqlTypeOther","length":38,"domain":null,"defaultValue":null}],"features":[{"attributes":{"OBJECTID":2830,"ADM0_NAME":"PHILIPPINES","DateOfDataEntry":1580342400000,"cum_conf":1,"NewCase":1,"CENTER_LON":122.87360743,"CENTER_LAT":11.74740203,"ADM0_VIZ_NAME":"Philippines","GUID":"73f7c9bf-ebf4-48dd-b4a8-ce2005c7b2fd","Short_Name_ZH":"菲律宾","Short_Name_FR":"Philippines","Short_Name_ES":"Filipinas","Short_Name_RU":"Филиппины","Short_Name_AR":"الفلبين","GlobalID":"92da2477-626b-46e2-a6f4-7e4e40ed589f"},"geometry":{"x":122.87360742700002,"y":11.747402026000032}},{"attributes":{"OBJECTID":2831,"ADM0_NAME":"PHILIPPINES","DateOfDataEntry":1580428800000,"cum_conf":1,"NewCase":0,"CENTER_LON":122.87360743,"CENTER_LAT":11.74740203,"ADM0_VIZ_NAME":"Philippines","GUID":"73f7c9bf-ebf4-48dd-b4a8-ce2005c7b2fd","Short_Name_ZH":"菲律宾","Short_Name_FR":"Philippines","Short_Name_ES":"Filipinas","Short_Name_RU":"Филиппины","Short_Name_AR":"الفلبين","GlobalID":"1003a0c6-1d19-4f9c-a798-fdebcbe6f3b9"},"geometry":{"x":122.87360742700002,"y":11.747402026000032}},{"attributes":{"OBJECTID":2832,"ADM0_NAME":"PHILIPPINES","DateOfDataEntry":1580515200000,"cum_conf":1,"NewCase":0,"CENTER_LON":122.87360743,"CENTER_LAT":11.74740203,"ADM0_VIZ_NAME":"Philippines","GUID":"73f7c9bf-ebf4-48dd-b4a8-ce2005c7b2fd","Short_Name_ZH":"菲律宾","Short_Name_FR":"Philippines","Short_Name_ES":"Filipinas","Short_Name_RU":"Филиппины","Short_Name_AR":"الفلبين","GlobalID":"36a72244-870b-4f7b-8b5a-a5e36a0e5aa4"},"geometry":{"x":122.87360742700002,"y":11.747402026000032}},{"attributes":{"OBJECTID":2833,"ADM0_NAME":"PHILIPPINES","DateOfDataEntry":1580601600000,"cum_conf":2,"NewCase":1,"CENTER_LON":122.87360743,"CENTER_LAT":11.74740203,"ADM0_VIZ_NAME":"Philippines","GUID":"73f7c9bf-ebf4-48dd-b4a8-ce2005c7b2fd","Short_Name_ZH":"菲律宾","Short_Name_FR":"Philippines","Short_Name_ES":"Filipinas","Short_Name_RU":"Филиппины","Short_Name_AR":"الفلبين","GlobalID":"35a16a29-d5a0-4993-ae82-02d424ab2bf2"},"geometry":{"x":122.87360742700002,"y":11.747402026000032}},{"attributes":{"OBJECTID":2834,"ADM0_NAME":"PHILIPPINES","DateOfDataEntry":1580688000000,"cum_conf":2,"NewCase":0,"CENTER_LON":122.87360743,"CENTER_LAT":11.74740203,"ADM0_VIZ_NAME":"Philippines","GUID":"73f7c9bf-ebf4-48dd-b4a8-ce2005c7b2fd","Short_Name_ZH":"菲律宾","Short_Name_FR":"Philippines","Short_Name_ES":"Filipinas","Short_Name_RU":"Филиппины","Short_Name_AR":"الفلبين","GlobalID":"3a2c35f3-d7bb-4534-8da9-52ad3ff31ab7"},"geometry":{"x":122.87360742700002,"y":11.747402026000032}},{"attributes":{"OBJECTID":2835,"ADM0_NAME":"PHILIPPINES","DateOfDataEntry":1580774400000,"cum_conf":3,"NewCase":1,"CENTER_LON":122.87360743,"CENTER_LAT":11.74740203,"ADM0_VIZ_NAME":"Philippines","GUID":"73f7c9bf-ebf4-48dd-b4a8-ce2005c7b2fd","Short_Name_ZH":"菲律宾","Short_Name_FR":"Philippines","Short_Name_ES":"Filipinas","Short_Name_RU":"Филиппины","Short_Name_AR":"الفلبين","GlobalID":"c551cf96-2231-43d2-afb3-7f06cdf0ee97"},"geometry":{"x":122.87360742700002,"y":11.747402026000032}},{"attributes":{"OBJECTID":2836,"ADM0_NAME":"PHILIPPINES","DateOfDataEntry":1580860800000,"cum_conf":3,"NewCase":0,"CENTER_LON":122.87360743,"CENTER_LAT":11.74740203,"ADM0_VIZ_NAME":"Philippines","GUID":"73f7c9bf-ebf4-48dd-b4a8-ce2005c7b2fd","Short_Name_ZH":"菲律宾","Short_Name_FR":"Philippines","Short_Name_ES":"Filipinas","Short_Name_RU":"Филиппины","Short_Name_AR":"الفلبين","GlobalID":"a972af90-ddcd-4dcf-b9b6-58f3dc65ace6"},"geometry":{"x":122.87360742700002,"y":11.747402026000032}},{"attributes":{"OBJECTID":2837,"ADM0_NAME":"PHILIPPINES","DateOfDataEntry":1580947200000,"cum_conf":3,"NewCase":0,"CENTER_LON":122.87360743,"CENTER_LAT":11.74740203,"ADM0_VIZ_NAME":"Philippines","GUID":"73f7c9bf-ebf4-48dd-b4a8-ce2005c7b2fd","Short_Name_ZH":"菲律宾","Short_Name_FR":"Philippines","Short_Name_ES":"Filipinas","Short_Name_RU":"Филиппины","Short_Name_AR":"الفلبين","GlobalID":"1d9b10e7-7322-4445-8df8-011eec90ad09"},"geometry":{"x":122.87360742700002,"y":11.747402026000032}},{"attributes":{"OBJECTID":2838,"ADM0_NAME":"PHILIPPINES","DateOfDataEntry":1581033600000,"cum_conf":3,"NewCase":0,"CENTER_LON":122.87360743,"CENTER_LAT":11.74740203,"ADM0_VIZ_NAME":"Philippines","GUID":"73f7c9bf-ebf4-48dd-b4a8-ce2005c7b2fd","Short_Name_ZH":"菲律宾","Short_Name_FR":"Philippines","Short_Name_ES":"Filipinas","Short_Name_RU":"Филиппины","Short_Name_AR":"الفلبين","GlobalID":"a1154e16-cf14-408a-8a3e-0fe4e0ea2dc7"},"geometry":{"x":122.87360742700002,"y":11.747402026000032}},{"attributes":{"OBJECTID":2839,"ADM0_NAME":"PHILIPPINES","DateOfDataEntry":1581120000000,"cum_conf":3,"NewCase":0,"CENTER_LON":122.87360743,"CENTER_LAT":11.74740203,"ADM0_VIZ_NAME":"Philippines","GUID":"73f7c9bf-ebf4-48dd-b4a8-ce2005c7b2fd","Short_Name_ZH":"菲律宾","Short_Name_FR":"Philippines","Short_Name_ES":"Filipinas","Short_Name_RU":"Филиппины","Short_Name_AR":"الفلبين","GlobalID":"7c447abb-4ed8-49dc-9a68-1d99ad2cddfb"},"geometry":{"x":122.87360742700002,"y":11.747402026000032}},{"attributes":{"OBJECTID":2840,"ADM0_NAME":"PHILIPPINES","DateOfDataEntry":1581206400000,"cum_conf":3,"NewCase":0,"CENTER_LON":122.87360743,"CENTER_LAT":11.74740203,"ADM0_VIZ_NAME":"Philippines","GUID":"73f7c9bf-ebf4-48dd-b4a8-ce2005c7b2fd","Short_Name_ZH":"菲律宾","Short_Name_FR":"Philippines","Short_Name_ES":"Filipinas","Short_Name_RU":"Филиппины","Short_Name_AR":"الفلبين","GlobalID":"a54acce3-2469-4046-aa0b-0f6188e01226"},"geometry":{"x":122.87360742700002,"y":11.747402026000032}},{"attributes":{"OBJECTID":2841,"ADM0_NAME":"PHILIPPINES","DateOfDataEntry":1581292800000,"cum_conf":3,"NewCase":0,"CENTER_LON":122.87360743,"CENTER_LAT":11.74740203,"ADM0_VIZ_NAME":"Philippines","GUID":"73f7c9bf-ebf4-48dd-b4a8-ce2005c7b2fd","Short_Name_ZH":"菲律宾","Short_Name_FR":"Philippines","Short_Name_ES":"Filipinas","Short_Name_RU":"Филиппины","Short_Name_AR":"الفلبين","GlobalID":"fc444a09-b970-475a-a56e-4b83816fb61d"},"geometry":{"x":122.87360742700002,"y":11.747402026000032}},{"attributes":{"OBJECTID":2842,"ADM0_NAME":"PHILIPPINES","DateOfDataEntry":1581379200000,"cum_conf":3,"NewCase":0,"CENTER_LON":122.87360743,"CENTER_LAT":11.74740203,"ADM0_VIZ_NAME":"Philippines","GUID":"73f7c9bf-ebf4-48dd-b4a8-ce2005c7b2fd","Short_Name_ZH":"菲律宾","Short_Name_FR":"Philippines","Short_Name_ES":"Filipinas","Short_Name_RU":"Филиппины","Short_Name_AR":"الفلبين","GlobalID":"35f72c1f-6c52-440a-9696-56e466e9a5da"},"geometry":{"x":122.87360742700002,"y":11.747402026000032}},{"attributes":{"OBJECTID":2843,"ADM0_NAME":"PHILIPPINES","DateOfDataEntry":1581465600000,"cum_conf":3,"NewCase":0,"CENTER_LON":122.87360743,"CENTER_LAT":11.74740203,"ADM0_VIZ_NAME":"Philippines","GUID":"73f7c9bf-ebf4-48dd-b4a8-ce2005c7b2fd","Short_Name_ZH":"菲律宾","Short_Name_FR":"Philippines","Short_Name_ES":"Filipinas","Short_Name_RU":"Филиппины","Short_Name_AR":"الفلبين","GlobalID":"7dc97a7c-7b79-43ae-bae9-f4b20901d6a4"},"geometry":{"x":122.87360742700002,"y":11.747402026000032}},{"attributes":{"OBJECTID":2844,"ADM0_NAME":"PHILIPPINES","DateOfDataEntry":1581552000000,"cum_conf":3,"NewCase":0,"CENTER_LON":122.87360743,"CENTER_LAT":11.74740203,"ADM0_VIZ_NAME":"Philippines","GUID":"73f7c9bf-ebf4-48dd-b4a8-ce2005c7b2fd","Short_Name_ZH":"菲律宾","Short_Name_FR":"Philippines","Short_Name_ES":"Filipinas","Short_Name_RU":"Филиппины","Short_Name_AR":"الفلبين","GlobalID":"67520bb1-ee7c-4ee3-8710-8a8a61fb85ea"},"geometry":{"x":122.87360742700002,"y":11.747402026000032}},{"attributes":{"OBJECTID":2845,"ADM0_NAME":"PHILIPPINES","DateOfDataEntry":1581638400000,"cum_conf":3,"NewCase":0,"CENTER_LON":122.87360743,"CENTER_LAT":11.74740203,"ADM0_VIZ_NAME":"Philippines","GUID":"73f7c9bf-ebf4-48dd-b4a8-ce2005c7b2fd","Short_Name_ZH":"菲律宾","Short_Name_FR":"Philippines","Short_Name_ES":"Filipinas","Short_Name_RU":"Филиппины","Short_Name_AR":"الفلبين","GlobalID":"bf232b91-6a2b-4b90-9cf4-77cfa3226cf6"},"geometry":{"x":122.87360742700002,"y":11.747402026000032}},{"attributes":{"OBJECTID":2846,"ADM0_NAME":"PHILIPPINES","DateOfDataEntry":1581724800000,"cum_conf":3,"NewCase":0,"CENTER_LON":122.87360743,"CENTER_LAT":11.74740203,"ADM0_VIZ_NAME":"Philippines","GUID":"73f7c9bf-ebf4-48dd-b4a8-ce2005c7b2fd","Short_Name_ZH":"菲律宾","Short_Name_FR":"Philippines","Short_Name_ES":"Filipinas","Short_Name_RU":"Филиппины","Short_Name_AR":"الفلبين","GlobalID":"3352acfd-c979-4ef3-ad91-c842ad9440e6"},"geometry":{"x":122.87360742700002,"y":11.747402026000032}},{"attributes":{"OBJECTID":2847,"ADM0_NAME":"PHILIPPINES","DateOfDataEntry":1581811200000,"cum_conf":3,"NewCase":0,"CENTER_LON":122.87360743,"CENTER_LAT":11.74740203,"ADM0_VIZ_NAME":"Philippines","GUID":"73f7c9bf-ebf4-48dd-b4a8-ce2005c7b2fd","Short_Name_ZH":"菲律宾","Short_Name_FR":"Philippines","Short_Name_ES":"Filipinas","Short_Name_RU":"Филиппины","Short_Name_AR":"الفلبين","GlobalID":"d6abd798-08c8-4013-ba6b-21c3bb72d938"},"geometry":{"x":122.87360742700002,"y":11.747402026000032}},{"attributes":{"OBJECTID":2848,"ADM0_NAME":"PHILIPPINES","DateOfDataEntry":1581897600000,"cum_conf":3,"NewCase":0,"CENTER_LON":122.87360743,"CENTER_LAT":11.74740203,"ADM0_VIZ_NAME":"Philippines","GUID":"73f7c9bf-ebf4-48dd-b4a8-ce2005c7b2fd","Short_Name_ZH":"菲律宾","Short_Name_FR":"Philippines","Short_Name_ES":"Filipinas","Short_Name_RU":"Филиппины","Short_Name_AR":"الفلبين","GlobalID":"de291560-59fd-489e-b74c-8a2324482277"},"geometry":{"x":122.87360742700002,"y":11.747402026000032}},{"attributes":{"OBJECTID":2849,"ADM0_NAME":"PHILIPPINES","DateOfDataEntry":1581984000000,"cum_conf":3,"NewCase":0,"CENTER_LON":122.87360743,"CENTER_LAT":11.74740203,"ADM0_VIZ_NAME":"Philippines","GUID":"73f7c9bf-ebf4-48dd-b4a8-ce2005c7b2fd","Short_Name_ZH":"菲律宾","Short_Name_FR":"Philippines","Short_Name_ES":"Filipinas","Short_Name_RU":"Филиппины","Short_Name_AR":"الفلبين","GlobalID":"08dd0143-ba58-4d21-837f-59a032e87b55"},"geometry":{"x":122.87360742700002,"y":11.747402026000032}},{"attributes":{"OBJECTID":2850,"ADM0_NAME":"PHILIPPINES","DateOfDataEntry":1582070400000,"cum_conf":3,"NewCase":0,"CENTER_LON":122.87360743,"CENTER_LAT":11.74740203,"ADM0_VIZ_NAME":"Philippines","GUID":"73f7c9bf-ebf4-48dd-b4a8-ce2005c7b2fd","Short_Name_ZH":"菲律宾","Short_Name_FR":"Philippines","Short_Name_ES":"Filipinas","Short_Name_RU":"Филиппины","Short_Name_AR":"الفلبين","GlobalID":"d881d8e7-3299-43ef-8a43-898ac9124429"},"geometry":{"x":122.87360742700002,"y":11.747402026000032}},{"attributes":{"OBJECTID":2851,"ADM0_NAME":"PHILIPPINES","DateOfDataEntry":1582156800000,"cum_conf":3,"NewCase":0,"CENTER_LON":122.87360743,"CENTER_LAT":11.74740203,"ADM0_VIZ_NAME":"Philippines","GUID":"73f7c9bf-ebf4-48dd-b4a8-ce2005c7b2fd","Short_Name_ZH":"菲律宾","Short_Name_FR":"Philippines","Short_Name_ES":"Filipinas","Short_Name_RU":"Филиппины","Short_Name_AR":"الفلبين","GlobalID":"ce725062-fc41-467c-987d-d4962974f952"},"geometry":{"x":122.87360742700002,"y":11.747402026000032}},{"attributes":{"OBJECTID":2852,"ADM0_NAME":"PHILIPPINES","DateOfDataEntry":1582243200000,"cum_conf":3,"NewCase":0,"CENTER_LON":122.87360743,"CENTER_LAT":11.74740203,"ADM0_VIZ_NAME":"Philippines","GUID":"73f7c9bf-ebf4-48dd-b4a8-ce2005c7b2fd","Short_Name_ZH":"菲律宾","Short_Name_FR":"Philippines","Short_Name_ES":"Filipinas","Short_Name_RU":"Филиппины","Short_Name_AR":"الفلبين","GlobalID":"49242b3c-26b2-475b-8601-4cbd05206d07"},"geometry":{"x":122.87360742700002,"y":11.747402026000032}},{"attributes":{"OBJECTID":2853,"ADM0_NAME":"PHILIPPINES","DateOfDataEntry":1582329600000,"cum_conf":3,"NewCase":0,"CENTER_LON":122.87360743,"CENTER_LAT":11.74740203,"ADM0_VIZ_NAME":"Philippines","GUID":"73f7c9bf-ebf4-48dd-b4a8-ce2005c7b2fd","Short_Name_ZH":"菲律宾","Short_Name_FR":"Philippines","Short_Name_ES":"Filipinas","Short_Name_RU":"Филиппины","Short_Name_AR":"الفلبين","GlobalID":"609c478f-cc7f-4421-9566-da9e482409da"},"geometry":{"x":122.87360742700002,"y":11.747402026000032}},{"attributes":{"OBJECTID":2854,"ADM0_NAME":"PHILIPPINES","DateOfDataEntry":1582416000000,"cum_conf":3,"NewCase":0,"CENTER_LON":122.87360743,"CENTER_LAT":11.74740203,"ADM0_VIZ_NAME":"Philippines","GUID":"73f7c9bf-ebf4-48dd-b4a8-ce2005c7b2fd","Short_Name_ZH":"菲律宾","Short_Name_FR":"Philippines","Short_Name_ES":"Filipinas","Short_Name_RU":"Филиппины","Short_Name_AR":"الفلبين","GlobalID":"aca9a661-994b-4e53-9910-6e6bef8b1e6d"},"geometry":{"x":122.87360742700002,"y":11.747402026000032}},{"attributes":{"OBJECTID":2855,"ADM0_NAME":"PHILIPPINES","DateOfDataEntry":1582502400000,"cum_conf":3,"NewCase":0,"CENTER_LON":122.87360743,"CENTER_LAT":11.74740203,"ADM0_VIZ_NAME":"Philippines","GUID":"73f7c9bf-ebf4-48dd-b4a8-ce2005c7b2fd","Short_Name_ZH":"菲律宾","Short_Name_FR":"Philippines","Short_Name_ES":"Filipinas","Short_Name_RU":"Филиппины","Short_Name_AR":"الفلبين","GlobalID":"0337b2f8-4253-43ac-8584-7707c3b524b7"},"geometry":{"x":122.87360742700002,"y":11.747402026000032}},{"attributes":{"OBJECTID":2856,"ADM0_NAME":"PHILIPPINES","DateOfDataEntry":1582588800000,"cum_conf":3,"NewCase":0,"CENTER_LON":122.87360743,"CENTER_LAT":11.74740203,"ADM0_VIZ_NAME":"Philippines","GUID":"73f7c9bf-ebf4-48dd-b4a8-ce2005c7b2fd","Short_Name_ZH":"菲律宾","Short_Name_FR":"Philippines","Short_Name_ES":"Filipinas","Short_Name_RU":"Филиппины","Short_Name_AR":"الفلبين","GlobalID":"dfbfe0cd-bb28-4bab-80cc-ceaf709b98dc"},"geometry":{"x":122.87360742700002,"y":11.747402026000032}},{"attributes":{"OBJECTID":2857,"ADM0_NAME":"PHILIPPINES","DateOfDataEntry":1582675200000,"cum_conf":3,"NewCase":0,"CENTER_LON":122.87360743,"CENTER_LAT":11.74740203,"ADM0_VIZ_NAME":"Philippines","GUID":"73f7c9bf-ebf4-48dd-b4a8-ce2005c7b2fd","Short_Name_ZH":"菲律宾","Short_Name_FR":"Philippines","Short_Name_ES":"Filipinas","Short_Name_RU":"Филиппины","Short_Name_AR":"الفلبين","GlobalID":"1f7580b9-c794-4a00-a938-240206629d44"},"geometry":{"x":122.87360742700002,"y":11.747402026000032}},{"attributes":{"OBJECTID":2858,"ADM0_NAME":"PHILIPPINES","DateOfDataEntry":1582761600000,"cum_conf":3,"NewCase":0,"CENTER_LON":122.87360743,"CENTER_LAT":11.74740203,"ADM0_VIZ_NAME":"Philippines","GUID":"73f7c9bf-ebf4-48dd-b4a8-ce2005c7b2fd","Short_Name_ZH":"菲律宾","Short_Name_FR":"Philippines","Short_Name_ES":"Filipinas","Short_Name_RU":"Филиппины","Short_Name_AR":"الفلبين","GlobalID":"ede0dc47-fd46-464e-8d33-9680672afdd7"},"geometry":{"x":122.87360742700002,"y":11.747402026000032}},{"attributes":{"OBJECTID":2859,"ADM0_NAME":"PHILIPPINES","DateOfDataEntry":1582848000000,"cum_conf":3,"NewCase":0,"CENTER_LON":122.87360743,"CENTER_LAT":11.74740203,"ADM0_VIZ_NAME":"Philippines","GUID":"73f7c9bf-ebf4-48dd-b4a8-ce2005c7b2fd","Short_Name_ZH":"菲律宾","Short_Name_FR":"Philippines","Short_Name_ES":"Filipinas","Short_Name_RU":"Филиппины","Short_Name_AR":"الفلبين","GlobalID":"5d4a2067-f94e-43a1-aa6f-8c7486593460"},"geometry":{"x":122.87360742700002,"y":11.747402026000032}},{"attributes":{"OBJECTID":2860,"ADM0_NAME":"PHILIPPINES","DateOfDataEntry":1582934400000,"cum_conf":3,"NewCase":0,"CENTER_LON":122.87360743,"CENTER_LAT":11.74740203,"ADM0_VIZ_NAME":"Philippines","GUID":"73f7c9bf-ebf4-48dd-b4a8-ce2005c7b2fd","Short_Name_ZH":"菲律宾","Short_Name_FR":"Philippines","Short_Name_ES":"Filipinas","Short_Name_RU":"Филиппины","Short_Name_AR":"الفلبين","GlobalID":"1e0de58a-1efa-46b8-9436-54838b8027dc"},"geometry":{"x":122.87360742700002,"y":11.747402026000032}},{"attributes":{"OBJECTID":2861,"ADM0_NAME":"PHILIPPINES","DateOfDataEntry":1583020800000,"cum_conf":3,"NewCase":0,"CENTER_LON":122.87360743,"CENTER_LAT":11.74740203,"ADM0_VIZ_NAME":"Philippines","GUID":"73f7c9bf-ebf4-48dd-b4a8-ce2005c7b2fd","Short_Name_ZH":"菲律宾","Short_Name_FR":"Philippines","Short_Name_ES":"Filipinas","Short_Name_RU":"Филиппины","Short_Name_AR":"الفلبين","GlobalID":"39e18b70-67f3-4f23-b4b4-7b5917b73895"},"geometry":{"x":122.87360742700002,"y":11.747402026000032}},{"attributes":{"OBJECTID":2862,"ADM0_NAME":"PHILIPPINES","DateOfDataEntry":1583107200000,"cum_conf":3,"NewCase":0,"CENTER_LON":122.87360743,"CENTER_LAT":11.74740203,"ADM0_VIZ_NAME":"Philippines","GUID":"73f7c9bf-ebf4-48dd-b4a8-ce2005c7b2fd","Short_Name_ZH":"菲律宾","Short_Name_FR":"Philippines","Short_Name_ES":"Filipinas","Short_Name_RU":"Филиппины","Short_Name_AR":"الفلبين","GlobalID":"e5656c27-83a8-4ff8-99b2-5a0eb7aeb9b4"},"geometry":{"x":122.87360742700002,"y":11.747402026000032}},{"attributes":{"OBJECTID":2863,"ADM0_NAME":"PHILIPPINES","DateOfDataEntry":1583193600000,"cum_conf":3,"NewCase":0,"CENTER_LON":122.87360743,"CENTER_LAT":11.74740203,"ADM0_VIZ_NAME":"Philippines","GUID":"73f7c9bf-ebf4-48dd-b4a8-ce2005c7b2fd","Short_Name_ZH":"菲律宾","Short_Name_FR":"Philippines","Short_Name_ES":"Filipinas","Short_Name_RU":"Филиппины","Short_Name_AR":"الفلبين","GlobalID":"4cd46a02-f731-41d8-9eb3-a6abcd9b8b33"},"geometry":{"x":122.87360742700002,"y":11.747402026000032}},{"attributes":{"OBJECTID":2864,"ADM0_NAME":"PHILIPPINES","DateOfDataEntry":1583280000000,"cum_conf":3,"NewCase":0,"CENTER_LON":122.87360743,"CENTER_LAT":11.74740203,"ADM0_VIZ_NAME":"Philippines","GUID":"73f7c9bf-ebf4-48dd-b4a8-ce2005c7b2fd","Short_Name_ZH":"菲律宾","Short_Name_FR":"Philippines","Short_Name_ES":"Filipinas","Short_Name_RU":"Филиппины","Short_Name_AR":"الفلبين","GlobalID":"22c0cab3-454e-4ac4-aaaa-8c64feea7210"},"geometry":{"x":122.87360742700002,"y":11.747402026000032}},{"attributes":{"OBJECTID":2865,"ADM0_NAME":"PHILIPPINES","DateOfDataEntry":1583366400000,"cum_conf":3,"NewCase":0,"CENTER_LON":122.87360743,"CENTER_LAT":11.74740203,"ADM0_VIZ_NAME":"Philippines","GUID":"73f7c9bf-ebf4-48dd-b4a8-ce2005c7b2fd","Short_Name_ZH":"菲律宾","Short_Name_FR":"Philippines","Short_Name_ES":"Filipinas","Short_Name_RU":"Филиппины","Short_Name_AR":"الفلبين","GlobalID":"94a2d529-e8e4-451f-b917-d745188f6f4b"},"geometry":{"x":122.87360742700002,"y":11.747402026000032}},{"attributes":{"OBJECTID":2866,"ADM0_NAME":"PHILIPPINES","DateOfDataEntry":1583452800000,"cum_conf":5,"NewCase":2,"CENTER_LON":122.87360743,"CENTER_LAT":11.74740203,"ADM0_VIZ_NAME":"Philippines","GUID":"73f7c9bf-ebf4-48dd-b4a8-ce2005c7b2fd","Short_Name_ZH":"菲律宾","Short_Name_FR":"Philippines","Short_Name_ES":"Filipinas","Short_Name_RU":"Филиппины","Short_Name_AR":"الفلبين","GlobalID":"daec9196-1663-4bf8-8082-1b7a88c3a611"},"geometry":{"x":122.87360742700002,"y":11.747402026000032}},{"attributes":{"OBJECTID":2867,"ADM0_NAME":"PHILIPPINES","DateOfDataEntry":1583539200000,"cum_conf":6,"NewCase":1,"CENTER_LON":122.87360743,"CENTER_LAT":11.74740203,"ADM0_VIZ_NAME":"Philippines","GUID":"73f7c9bf-ebf4-48dd-b4a8-ce2005c7b2fd","Short_Name_ZH":"菲律宾","Short_Name_FR":"Philippines","Short_Name_ES":"Filipinas","Short_Name_RU":"Филиппины","Short_Name_AR":"الفلبين","GlobalID":"d57e4fe0-d9e0-4478-a473-e9043a01e1bd"},"geometry":{"x":122.87360742700002,"y":11.747402026000032}},{"attributes":{"OBJECTID":2868,"ADM0_NAME":"PHILIPPINES","DateOfDataEntry":1583625600000,"cum_conf":6,"NewCase":0,"CENTER_LON":122.87360743,"CENTER_LAT":11.74740203,"ADM0_VIZ_NAME":"Philippines","GUID":"73f7c9bf-ebf4-48dd-b4a8-ce2005c7b2fd","Short_Name_ZH":"菲律宾","Short_Name_FR":"Philippines","Short_Name_ES":"Filipinas","Short_Name_RU":"Филиппины","Short_Name_AR":"الفلبين","GlobalID":"18a124e3-fa75-42aa-8ca3-05744bbab36a"},"geometry":{"x":122.87360742700002,"y":11.747402026000032}},{"attributes":{"OBJECTID":2869,"ADM0_NAME":"PHILIPPINES","DateOfDataEntry":1583712000000,"cum_conf":24,"NewCase":18,"CENTER_LON":122.87360743,"CENTER_LAT":11.74740203,"ADM0_VIZ_NAME":"Philippines","GUID":"73f7c9bf-ebf4-48dd-b4a8-ce2005c7b2fd","Short_Name_ZH":"菲律宾","Short_Name_FR":"Philippines","Short_Name_ES":"Filipinas","Short_Name_RU":"Филиппины","Short_Name_AR":"الفلبين","GlobalID":"6cd28edd-3384-4a5e-9f56-0d5d6227078d"},"geometry":{"x":122.87360742700002,"y":11.747402026000032}},{"attributes":{"OBJECTID":2870,"ADM0_NAME":"PHILIPPINES","DateOfDataEntry":1583798400000,"cum_conf":33,"NewCase":9,"CENTER_LON":122.87360743,"CENTER_LAT":11.74740203,"ADM0_VIZ_NAME":"Philippines","GUID":"73f7c9bf-ebf4-48dd-b4a8-ce2005c7b2fd","Short_Name_ZH":"菲律宾","Short_Name_FR":"Philippines","Short_Name_ES":"Filipinas","Short_Name_RU":"Филиппины","Short_Name_AR":"الفلبين","GlobalID":"d3a3f924-4572-4d27-9ddf-c627121f1998"},"geometry":{"x":122.87360742700002,"y":11.747402026000032}},{"attributes":{"OBJECTID":2871,"ADM0_NAME":"PHILIPPINES","DateOfDataEntry":1583884800000,"cum_conf":49,"NewCase":16,"CENTER_LON":122.87360743,"CENTER_LAT":11.74740203,"ADM0_VIZ_NAME":"Philippines","GUID":"73f7c9bf-ebf4-48dd-b4a8-ce2005c7b2fd","Short_Name_ZH":"菲律宾","Short_Name_FR":"Philippines","Short_Name_ES":"Filipinas","Short_Name_RU":"Филиппины","Short_Name_AR":"الفلبين","GlobalID":"bd4e4d81-021e-4f0f-bce5-a88998a42ed8"},"geometry":{"x":122.87360742700002,"y":11.747402026000032}},{"attributes":{"OBJECTID":2872,"ADM0_NAME":"PHILIPPINES","DateOfDataEntry":1583971200000,"cum_conf":52,"NewCase":3,"CENTER_LON":122.87360743,"CENTER_LAT":11.74740203,"ADM0_VIZ_NAME":"Philippines","GUID":"73f7c9bf-ebf4-48dd-b4a8-ce2005c7b2fd","Short_Name_ZH":"菲律宾","Short_Name_FR":"Philippines","Short_Name_ES":"Filipinas","Short_Name_RU":"Филиппины","Short_Name_AR":"الفلبين","GlobalID":"5415769a-b629-4dd4-a3e0-1b393932457f"},"geometry":{"x":122.87360742700002,"y":11.747402026000032}},{"attributes":{"OBJECTID":2873,"ADM0_NAME":"PHILIPPINES","DateOfDataEntry":1584057600000,"cum_conf":52,"NewCase":0,"CENTER_LON":122.87360743,"CENTER_LAT":11.74740203,"ADM0_VIZ_NAME":"Philippines","GUID":"73f7c9bf-ebf4-48dd-b4a8-ce2005c7b2fd","Short_Name_ZH":"菲律宾","Short_Name_FR":"Philippines","Short_Name_ES":"Filipinas","Short_Name_RU":"Филиппины","Short_Name_AR":"الفلبين","GlobalID":"8f9e0c52-ece5-4547-9332-769ba7ef1483"},"geometry":{"x":122.87360742700002,"y":11.747402026000032}},{"attributes":{"OBJECTID":2874,"ADM0_NAME":"PHILIPPINES","DateOfDataEntry":1584144000000,"cum_conf":64,"NewCase":12,"CENTER_LON":122.87360743,"CENTER_LAT":11.74740203,"ADM0_VIZ_NAME":"Philippines","GUID":"73f7c9bf-ebf4-48dd-b4a8-ce2005c7b2fd","Short_Name_ZH":"菲律宾","Short_Name_FR":"Philippines","Short_Name_ES":"Filipinas","Short_Name_RU":"Филиппины","Short_Name_AR":"الفلبين","GlobalID":"ba80b1c1-eb43-4a15-ba62-8f867c022bf8"},"geometry":{"x":122.87360742700002,"y":11.747402026000032}},{"attributes":{"OBJECTID":2875,"ADM0_NAME":"PHILIPPINES","DateOfDataEntry":1584230400000,"cum_conf":111,"NewCase":47,"CENTER_LON":122.87360743,"CENTER_LAT":11.74740203,"ADM0_VIZ_NAME":"Philippines","GUID":"73f7c9bf-ebf4-48dd-b4a8-ce2005c7b2fd","Short_Name_ZH":"菲律宾","Short_Name_FR":"Philippines","Short_Name_ES":"Filipinas","Short_Name_RU":"Филиппины","Short_Name_AR":"الفلبين","GlobalID":"046a2a84-0280-49b6-8c2a-fa3d8b7e5c46"},"geometry":{"x":122.87360742700002,"y":11.747402026000032}},{"attributes":{"OBJECTID":2876,"ADM0_NAME":"Philippines","DateOfDataEntry":1584316800000,"cum_conf":140,"NewCase":29,"CENTER_LON":122.87360743,"CENTER_LAT":11.74740203,"ADM0_VIZ_NAME":"Philippines","GUID":"73f7c9bf-ebf4-48dd-b4a8-ce2005c7b2fd","Short_Name_ZH":"菲律宾","Short_Name_FR":"Philippines","Short_Name_ES":"Filipinas","Short_Name_RU":"Филиппины","Short_Name_AR":"الفلبين","GlobalID":"65501c28-7da9-43c0-aa3b-c5f68efa97ee"},"geometry":{"x":122.87360742700002,"y":11.747402026000032}},{"attributes":{"OBJECTID":2877,"ADM0_NAME":"Philippines","DateOfDataEntry":1584403200000,"cum_conf":187,"NewCase":47,"CENTER_LON":122.87360743,"CENTER_LAT":11.74740203,"ADM0_VIZ_NAME":"Philippines","GUID":"73f7c9bf-ebf4-48dd-b4a8-ce2005c7b2fd","Short_Name_ZH":"菲律宾","Short_Name_FR":"Philippines","Short_Name_ES":"Filipinas","Short_Name_RU":"Филиппины","Short_Name_AR":"الفلبين","GlobalID":"ce975700-13ef-4740-b3b0-4ae7c206e902"},"geometry":{"x":122.87360742700002,"y":11.747402026000032}},{"attributes":{"OBJECTID":2878,"ADM0_NAME":"Philippines","DateOfDataEntry":1584489600000,"cum_conf":187,"NewCase":0,"CENTER_LON":122.87360743,"CENTER_LAT":11.74740203,"ADM0_VIZ_NAME":"Philippines","GUID":"73f7c9bf-ebf4-48dd-b4a8-ce2005c7b2fd","Short_Name_ZH":"菲律宾","Short_Name_FR":"Philippines","Short_Name_ES":"Filipinas","Short_Name_RU":"Филиппины","Short_Name_AR":"الفلبين","GlobalID":"43389c05-c8bb-4957-a93e-e682e0ed174d"},"geometry":{"x":122.87360742700002,"y":11.747402026000032}},{"attributes":{"OBJECTID":2879,"ADM0_NAME":"Philippines","DateOfDataEntry":1584576000000,"cum_conf":187,"NewCase":0,"CENTER_LON":122.87360743,"CENTER_LAT":11.74740203,"ADM0_VIZ_NAME":"Philippines","GUID":"73f7c9bf-ebf4-48dd-b4a8-ce2005c7b2fd","Short_Name_ZH":"菲律宾","Short_Name_FR":"Philippines","Short_Name_ES":"Filipinas","Short_Name_RU":"Филиппины","Short_Name_AR":"الفلبين","GlobalID":"e3f64038-d3bd-4c61-8c39-1c29837f5529"},"geometry":{"x":122.87360742700002,"y":11.747402026000032}},{"attributes":{"OBJECTID":2880,"ADM0_NAME":"Philippines","DateOfDataEntry":1584662400000,"cum_conf":217,"NewCase":30,"CENTER_LON":122.87360743,"CENTER_LAT":11.74740203,"ADM0_VIZ_NAME":"Philippines","GUID":"73f7c9bf-ebf4-48dd-b4a8-ce2005c7b2fd","Short_Name_ZH":"菲律宾","Short_Name_FR":"Philippines","Short_Name_ES":"Filipinas","Short_Name_RU":"Филиппины","Short_Name_AR":"الفلبين","GlobalID":"25e4fc95-8458-4c1e-8a77-2a0ddf52fd48"},"geometry":{"x":122.87360742700002,"y":11.747402026000032}},{"attributes":{"OBJECTID":2881,"ADM0_NAME":"Philippines","DateOfDataEntry":1584748800000,"cum_conf":307,"NewCase":90,"CENTER_LON":122.87360743,"CENTER_LAT":11.74740203,"ADM0_VIZ_NAME":"Philippines","GUID":"73f7c9bf-ebf4-48dd-b4a8-ce2005c7b2fd","Short_Name_ZH":"菲律宾","Short_Name_FR":"Philippines","Short_Name_ES":"Filipinas","Short_Name_RU":"Филиппины","Short_Name_AR":"الفلبين","GlobalID":"0d5ed9d5-e220-4676-9c9a-82aa3160f9ef"},"geometry":{"x":122.87360742700002,"y":11.747402026000032}},{"attributes":{"OBJECTID":2882,"ADM0_NAME":"Philippines","DateOfDataEntry":1584835200000,"cum_conf":380,"NewCase":73,"CENTER_LON":122.87360743,"CENTER_LAT":11.74740203,"ADM0_VIZ_NAME":"Philippines","GUID":"73f7c9bf-ebf4-48dd-b4a8-ce2005c7b2fd","Short_Name_ZH":"菲律宾","Short_Name_FR":"Philippines","Short_Name_ES":"Filipinas","Short_Name_RU":"Филиппины","Short_Name_AR":"الفلبين","GlobalID":"f333f9e9-1dd0-4320-842c-35685e8e073b"},"geometry":{"x":122.87360742700002,"y":11.747402026000032}},{"attributes":{"OBJECTID":2883,"ADM0_NAME":"Philippines","DateOfDataEntry":1584921600000,"cum_conf":396,"NewCase":16,"CENTER_LON":122.87360743,"CENTER_LAT":11.74740203,"ADM0_VIZ_NAME":"Philippines","GUID":"73f7c9bf-ebf4-48dd-b4a8-ce2005c7b2fd","Short_Name_ZH":"菲律宾","Short_Name_FR":"Philippines","Short_Name_ES":"Filipinas","Short_Name_RU":"Филиппины","Short_Name_AR":"الفلبين","GlobalID":"10fff8f7-47ad-465a-8d04-7b688e0f73ec"},"geometry":{"x":122.87360742700002,"y":11.747402026000032}},{"attributes":{"OBJECTID":2884,"ADM0_NAME":"Philippines","DateOfDataEntry":1585008000000,"cum_conf":462,"NewCase":66,"CENTER_LON":122.87360743,"CENTER_LAT":11.74740203,"ADM0_VIZ_NAME":"Philippines","GUID":"73f7c9bf-ebf4-48dd-b4a8-ce2005c7b2fd","Short_Name_ZH":"菲律宾","Short_Name_FR":"Philippines","Short_Name_ES":"Filipinas","Short_Name_RU":"Филиппины","Short_Name_AR":"الفلبين","GlobalID":"20dfe692-b70b-4592-bbf3-f4570d52540e"},"geometry":{"x":122.87360742700002,"y":11.747402026000032}}]}
