{"objectIdFieldName":"OBJECTID","uniqueIdField":{"name":"OBJECTID","isSystemMaintained":true},"globalIdFieldName":"","geometryType":"esriGeometryPoint","spatialReference":{"wkid":4326,"latestWkid":4326},"fields":[{"name":"OBJECTID","type":"esriFieldTypeOID","alias":"OBJECTID","sqlType":"sqlTypeOther","domain":null,"defaultValue":null},{"name":"ADM0_NAME","type":"esriFieldTypeString","alias":"ADM0_NAME","sqlType":"sqlTypeOther","length":255,"domain":null,"defaultValue":null},{"name":"DateOfDataEntry","type":"esriFieldTypeDate","alias":"DateOfDataEntry","sqlType":"sqlTypeOther","length":8,"domain":null,"defaultValue":null},{"name":"cum_conf","type":"esriFieldTypeInteger","alias":"cum_conf","sqlType":"sqlTypeOther","domain":null,"defaultValue":null},{"name":"NewCase","type":"esriFieldTypeInteger","alias":"NewCase","sqlType":"sqlTypeOther","domain":null,"defaultValue":null},{"name":"CENTER_LON","type":"esriFieldTypeDouble","alias":"CENTER_LON","sqlType":"sqlTypeOther","domain":null,"defaultValue":null},{"name":"CENTER_LAT","type":"esriFieldTypeDouble","alias":"CENTER_LAT","sqlType":"sqlTypeOther","domain":null,"defaultValue":null},{"name":"ADM0_VIZ_NAME","type":"esriFieldTypeString","alias":"ADM0_VIZ_NAME","sqlType":"sqlTypeOther","length":255,"domain":null,"defaultValue":null},{"name":"GUID","type":"esriFieldTypeGUID","alias":"GUID","sqlType":"sqlTypeOther","length":38,"domain":null,"defaultValue":null},{"name":"Short_Name_ZH","type":"esriFieldTypeString","alias":"Short_Name_ZH","sqlType":"sqlTypeOther","length":255,"domain":null,"defaultValue":null},{"name":"Short_Name_FR","type":"esriFieldTypeString","alias":"Short_Name_FR","sqlType":"sqlTypeOther","length":255,"domain":null,"defaultValue":null},{"name":"Short_Name_ES","type":"esriFieldTypeString","alias":"Short_Name_ES","sqlType":"sqlTypeOther","length":255,"domain":null,"defaultValue":null},{"name":"Short_Name_RU","type":"esriFieldTypeString","alias":"Short_Name_RU","sqlType":"sqlTypeOther","length":255,"domain":null,"defaultValue":null},{"name":"Short_Name_AR","type":"esriFieldTypeString","alias":"Short_Name_AR","sqlType":"sqlTypeOther","length":255,"domain":null,"defaultValue":null}],"features":[{"attributes":{"OBJECTID":5692,"ADM0_NAME":"Turks and Caicos Islands","DateOfDataEntry":1585008000000,"cum_conf":1,"NewCase":1,"CENTER_LON":-71.88207917,"CENTER_LAT":21.80869292,"ADM0_VIZ_NAME":"Turks and Caicos Islands","GUID":"370668bf-3302-4cb1-928d-261a3fdd09ee","Short_Name_ZH":"特克斯和凯科斯群岛\r\n","Short_Name_FR":null,"Short_Name_ES":null,"Short_Name_RU":null,"Short_Name_AR":null},"geometry":{"x":-71.882079171999976,"y":21.808692919000066}},{"attributes":{"OBJECTID":5693,"ADM0_NAME":"Turks and Caicos Islands","DateOfDataEntry":1585094400000,"cum_conf":1,"NewCase":0,"CENTER_LON":-71.88207917,"CENTER_LAT":21.80869292,"ADM0_VIZ_NAME":"Turks and Caicos Islands","GUID":"370668bf-3302-4cb1-928d-261a3fdd09ee","Short_Name_ZH":"特克斯和凯科斯群岛\r\n","Short_Name_FR":null,"Short_Name_ES":null,"Short_Name_RU":null,"Short_Name_AR":null},"geometry":{"x":-71.882079171999976,"y":21.808692919000066}},{"attributes":{"OBJECTID":5694,"ADM0_NAME":"Turks and Caicos Islands","DateOfDataEntry":1585180800000,"cum_conf":1,"NewCase":0,"CENTER_LON":-71.88207917,"CENTER_LAT":21.80869292,"ADM0_VIZ_NAME":"Turks and Caicos Islands","GUID":"370668bf-3302-4cb1-928d-261a3fdd09ee","Short_Name_ZH":"特克斯和凯科斯群岛\r\n","Short_Name_FR":null,"Short_Name_ES":null,"Short_Name_RU":null,"Short_Name_AR":null},"geometry":{"x":-71.882079171999976,"y":21.808692919000066}},{"attributes":{"OBJECTID":5695,"ADM0_NAME":"Turks and Caicos Islands","DateOfDataEntry":1585267200000,"cum_conf":2,"NewCase":1,"CENTER_LON":-71.88207917,"CENTER_LAT":21.80869292,"ADM0_VIZ_NAME":"Turks and Caicos Islands","GUID":"370668bf-3302-4cb1-928d-261a3fdd09ee","Short_Name_ZH":"特克斯和凯科斯群岛\r\n","Short_Name_FR":null,"Short_Name_ES":null,"Short_Name_RU":null,"Short_Name_AR":null},"geometry":{"x":-71.882079171999976,"y":21.808692919000066}},{"attributes":{"OBJECTID":5696,"ADM0_NAME":"Turks and Caicos Islands","DateOfDataEntry":1585353600000,"cum_conf":2,"NewCase":0,"CENTER_LON":-71.88207917,"CENTER_LAT":21.80869292,"ADM0_VIZ_NAME":"Turks and Caicos Islands","GUID":"370668bf-3302-4cb1-928d-261a3fdd09ee","Short_Name_ZH":"特克斯和凯科斯群岛\r\n","Short_Name_FR":null,"Short_Name_ES":null,"Short_Name_RU":null,"Short_Name_AR":null},"geometry":{"x":-71.882079171999976,"y":21.808692919000066}},{"attributes":{"OBJECTID":5697,"ADM0_NAME":"Turks and Caicos Islands","DateOfDataEntry":1585440000000,"cum_conf":2,"NewCase":0,"CENTER_LON":-71.88207917,"CENTER_LAT":21.80869292,"ADM0_VIZ_NAME":"Turks and Caicos Islands","GUID":"370668bf-3302-4cb1-928d-261a3fdd09ee","Short_Name_ZH":"特克斯和凯科斯群岛\r\n","Short_Name_FR":null,"Short_Name_ES":null,"Short_Name_RU":null,"Short_Name_AR":null},"geometry":{"x":-71.882079171999976,"y":21.808692919000066}},{"attributes":{"OBJECTID":5698,"ADM0_NAME":"Turks and Caicos Islands","DateOfDataEntry":1585526400000,"cum_conf":4,"NewCase":2,"CENTER_LON":-71.88207917,"CENTER_LAT":21.80869292,"ADM0_VIZ_NAME":"Turks and Caicos Islands","GUID":"370668bf-3302-4cb1-928d-261a3fdd09ee","Short_Name_ZH":"特克斯和凯科斯群岛\r\n","Short_Name_FR":null,"Short_Name_ES":null,"Short_Name_RU":null,"Short_Name_AR":null},"geometry":{"x":-71.882079171999976,"y":21.808692919000066}},{"attributes":{"OBJECTID":5699,"ADM0_NAME":"Turks and Caicos Islands","DateOfDataEntry":1585612800000,"cum_conf":5,"NewCase":1,"CENTER_LON":-71.88207917,"CENTER_LAT":21.80869292,"ADM0_VIZ_NAME":"Turks and Caicos Islands","GUID":"370668bf-3302-4cb1-928d-261a3fdd09ee","Short_Name_ZH":"特克斯和凯科斯群岛\r\n","Short_Name_FR":null,"Short_Name_ES":null,"Short_Name_RU":null,"Short_Name_AR":null},"geometry":{"x":-71.882079171999976,"y":21.808692919000066}},{"attributes":{"OBJECTID":5700,"ADM0_NAME":"Turks and Caicos Islands","DateOfDataEntry":1585699200000,"cum_conf":5,"NewCase":0,"CENTER_LON":-71.88207917,"CENTER_LAT":21.80869292,"ADM0_VIZ_NAME":"Turks and Caicos Islands","GUID":"370668bf-3302-4cb1-928d-261a3fdd09ee","Short_Name_ZH":"特克斯和凯科斯群岛\r\n","Short_Name_FR":null,"Short_Name_ES":null,"Short_Name_RU":null,"Short_Name_AR":null},"geometry":{"x":-71.882079171999976,"y":21.808692919000066}},{"attributes":{"OBJECTID":5701,"ADM0_NAME":"Turks and Caicos Islands","DateOfDataEntry":1585785600000,"cum_conf":5,"NewCase":0,"CENTER_LON":-71.88207917,"CENTER_LAT":21.80869292,"ADM0_VIZ_NAME":"Turks and Caicos Islands","GUID":"370668bf-3302-4cb1-928d-261a3fdd09ee","Short_Name_ZH":"特克斯和凯科斯群岛\r\n","Short_Name_FR":null,"Short_Name_ES":null,"Short_Name_RU":null,"Short_Name_AR":null},"geometry":{"x":-71.882079171999976,"y":21.808692919000066}}]}
